{
  "id": 74,
  "filename": "第74课-系统世界观与跨学科思维-系统思维基础.md",
  "title": "第72课：系统世界观与跨学科思维（从部分到整体的认知革命）",
  "module": "系统思维基础",
  "grade": "4年级及以上（已完成入门阶段学习）",
  "duration": "",
  "objective": "",
  "sections": [
    {
      "id": "-",
      "title": "📚 课程信息",
      "type": "general",
      "content": "- **学习时长**：23分钟（技能掌握15分钟 + 深度拓展8分钟）\n- **核心技能**：建立系统化的世界观，掌握跨学科思维方法，形成整体性认知能力\n\n---",
      "subsections": []
    },
    {
      "id": "-",
      "title": "🎯 学习目标",
      "type": "general",
      "content": "学完这节课，你将能够：\n- ✅ 理解系统世界观的核心理念和价值\n- ✅ 掌握跨学科思维的基本方法和应用\n- ✅ 学会用系统视角分析复杂现象和问题\n- ✅ 建立整体性、关联性、动态性的思维习惯\n\n---",
      "subsections": []
    },
    {
      "id": "-3",
      "title": "📖 概念导入（3分钟）",
      "type": "introduction",
      "content": "### 🤔 思考一下\n\n想象你面前有一幅巨大的拼图：\n\n**传统思维方式**：\n- 专注于每一块拼图的细节\n- 分别研究每块拼图的颜色、形状、纹理\n- 把每块拼图分类整理\n\n**系统思维方式**：\n- 关注拼图块之间的连接关系\n- 思考每块拼图在整体图案中的作用\n- 理解完整图案所要表达的意义\n\n现在想象这幅拼图就是我们生活的世界：每个学科、每个现象、每个问题都是其中的一块拼图。你更愿意用哪种方式来理解这个世界？\n\n### 💡 核心概念\n\n#### **什么是系统世界观？**\n\n**系统世界观的定义**：\n- **基本含义**：把世界看作一个相互关联、相互影响的整体系统\n- **核心特征**：强调整体性、关联性、层次性、动态性、目的性\n- **重要价值**：帮助我们更全面、更深入地理解复杂世界\n\n**系统世界观的核心理念**：\n1. **整体性**：世界是一个统一的整体，部分只有在整体中才有意义\n2. **关联性**：万事万物都是相互关联的，没有孤立存在的事物\n3. **层次性**：世界具有多层次结构，每个层次都有其特殊规律\n4. **动态性**：世界处于不断变化发展中，静止是相对的\n5. **目的性**：系统的存在和发展都有其目的和方向\n\n#### **什么是跨学科思维？**\n\n**跨学科思维的定义**：\n- **基本含义**：运用多个学科的知识、方法和视角来理解和解决问题\n- **核心特征**：整合性、创新性、实用性、开放性\n- **重要作用**：突破学科界限，产生新的认知和解决方案\n\n**跨学科思维的必要性**：\n- **现实世界的复杂性**：真实问题往往涉及多个领域\n- **知识的相互渗透**：不同学科之间存在内在联系\n- **创新的需要**：重大突破往往发生在学科交叉点\n- **未来发展趋势**：21世纪是跨学科合作的时代\n\n---",
      "subsections": [
        {
          "id": "-",
          "title": "🤔 思考一下",
          "type": "reflection",
          "content": ""
        },
        {
          "id": "-",
          "title": "💡 核心概念",
          "type": "content",
          "content": ""
        }
      ]
    },
    {
      "id": "-5",
      "title": "🎬 案例展示（5分钟）",
      "type": "case-study",
      "content": "### 🌍 案例1：气候变化的系统性分析\n\n让我们用系统世界观和跨学科思维来理解气候变化这个复杂问题：\n\n#### **传统分学科分析的局限**\n\n**物理学角度**：\n- 关注温室气体的物理性质\n- 研究大气辐射平衡\n- 分析温度变化规律\n\n**化学角度**：\n- 研究大气化学反应\n- 分析污染物的化学性质\n- 探讨化学循环过程\n\n**生物学角度**：\n- 研究生物对气候的响应\n- 分析生态系统变化\n- 探讨物种适应机制\n\n**经济学角度**：\n- 计算气候变化的经济损失\n- 分析减排的经济成本\n- 研究绿色经济发展\n\n**问题**：每个学科都只看到了问题的一个方面，难以形成完整认识和有效解决方案。\n\n#### **系统性跨学科分析**\n\n**气候系统的整体性**：\n- **大气系统**：温室气体浓度、大气环流、极端天气\n- **海洋系统**：海水温度、洋流变化、海平面上升\n- **陆地系统**：冰川融化、植被变化、土壤退化\n- **生物系统**：物种迁移、生态平衡、生物多样性\n\n**多系统间的相互作用**：\n- **正反馈循环**：冰川融化→反射减少→温度上升→更多冰川融化\n- **负反馈调节**：温度上升→植物生长→CO2吸收→温度调节\n- **延迟效应**：今天的排放对未来几十年的气候产生影响\n- **阈值效应**：超过临界点可能引发不可逆转的变化\n\n**跨学科综合解决方案**：\n\n**技术层面**（物理学+工程学）：\n- 可再生能源技术开发\n- 碳捕获和储存技术\n- 节能减排技术创新\n\n**经济层面**（经济学+管理学）：\n- 碳税和碳交易机制\n- 绿色金融体系建设\n- 可持续发展商业模式\n\n**社会层面**（社会学+心理学）：\n- 公众环保意识提升\n- 生活方式转变引导\n- 社会行为改变机制\n\n**政策层面**（政治学+法学）：\n- 国际合作协议制定\n- 环保法律法规完善\n- 全球治理机制建设\n\n**生态层面**（生物学+环境学）：\n- 生态系统保护修复\n- 生物多样性维护\n- 自然解决方案推广\n\n#### **系统思维的价值体现**\n\n**整体性认识**：\n- 理解气候变化是一个涉及自然和社会多个系统的复杂问题\n- 认识到单一措施难以解决，需要系统性综合方案\n\n**关联性分析**：\n- 发现不同因素间的相互影响和反馈关系\n- 理解局部行动对全球系统的影响\n\n**动态性把握**：\n- 认识到气候系统的变化趋势和发展规律\n- 理解时间延迟和累积效应的重要性\n\n**层次性理解**：\n- 从个人、社区、国家、全球不同层次分析问题\n- 在不同层次设计相应的解决策略\n\n### 🏥 案例2：健康问题的跨学科分析\n\n让我们分析\"青少年近视率上升\"这个问题：\n\n#### **单学科分析的视角**\n\n**医学角度**：\n- 眼球结构变化\n- 视力矫正方法\n- 治疗技术发展\n\n**教育学角度**：\n- 学习负担过重\n- 用眼习惯不良\n- 教育方式改进\n\n**心理学角度**：\n- 学习压力影响\n- 行为习惯形成\n- 心理干预方法\n\n#### **跨学科系统分析**\n\n**生物医学系统**：\n- **遗传因素**：家族遗传倾向\n- **生理因素**：眼球发育规律\n- **病理因素**：近视形成机制\n\n**行为习惯系统**：\n- **用眼行为**：阅读距离、用眼时间、休息频率\n- **生活方式**：户外活动、睡眠质量、饮食营养\n- **学习习惯**：学习姿势、环境光线、电子设备使用\n\n**教育环境系统**：\n- **学校环境**：教室照明、课桌高度、课程安排\n- **家庭环境**：学习空间、家长监督、家庭氛围\n- **社会环境**：教育竞争、电子产品普及、生活节奏\n\n**社会文化系统**：\n- **教育文化**：重视学习成绩、忽视身体健康\n- **科技文化**：电子设备依赖、数字化生活\n- **健康文化**：健康意识薄弱、预防观念不足\n\n**跨学科综合干预方案**：\n\n**医学干预**：\n- 定期视力检查和早期干预\n- 科学的视力矫正和治疗\n\n**教育改革**：\n- 减轻学业负担，增加户外活动\n- 改善教学环境和方法\n\n**行为干预**：\n- 培养良好的用眼习惯\n- 建立健康的生活方式\n\n**环境改善**：\n- 优化学习和生活环境\n- 控制电子设备使用\n\n**社会倡导**：\n- 提高全社会的健康意识\n- 建立健康友好的社会环境\n\n🤔 **暂停思考**：通过这两个案例，你发现系统世界观和跨学科思维有什么优势？它们如何帮助我们更好地理解和解决复杂问题？\n\n---",
      "subsections": [
        {
          "id": "-1",
          "title": "🌍 案例1：气候变化的系统性分析",
          "type": "case",
          "content": ""
        },
        {
          "id": "-2",
          "title": "🏥 案例2：健康问题的跨学科分析",
          "type": "case",
          "content": ""
        }
      ]
    },
    {
      "id": "-5",
      "title": "🧠 核心内容（5分钟）",
      "type": "core-content",
      "content": "### 🎯 系统世界观的核心要素\n\n#### **1. 整体性思维**\n\n**整体优先原则**：\n- **整体决定部分**：部分的性质和功能由其在整体中的地位决定\n- **整体大于部分之和**：整体具有部分所没有的新特性\n- **部分服务整体**：部分的存在和发展要服务于整体目标\n\n**整体性分析方法**：\n- **统筹兼顾**：同时考虑多个方面和因素\n- **全局规划**：从整体角度制定策略和方案\n- **协调发展**：平衡各部分的发展需求\n\n#### **2. 关联性思维**\n\n**普遍联系原则**：\n- **内部联系**：系统内部各要素相互关联\n- **外部联系**：系统与环境相互影响\n- **层次联系**：不同层次系统间相互作用\n\n**关联性分析方法**：\n- **网络分析**：绘制要素间的关系网络\n- **影响分析**：分析一个变化对其他要素的影响\n- **反馈分析**：识别相互影响的反馈回路\n\n#### **3. 层次性思维**\n\n**层次结构原则**：\n- **多层次性**：系统具有多个层次结构\n- **层次涌现**：每个层次都有独特的性质\n- **层次互动**：不同层次间相互影响\n\n**层次性分析方法**：\n- **分层分析**：在不同层次分析问题\n- **跨层思考**：考虑跨层次的影响关系\n- **层次整合**：整合不同层次的解决方案\n\n#### **4. 动态性思维**\n\n**变化发展原则**：\n- **运动变化**：系统处于不断变化中\n- **发展趋势**：变化具有一定的方向性\n- **阶段特征**：发展过程具有阶段性\n\n**动态性分析方法**：\n- **趋势分析**：分析系统的发展趋势\n- **阶段分析**：识别发展的不同阶段\n- **预测分析**：预测未来的发展方向\n\n### 🔄 跨学科思维的实践方法\n\n#### **1. 知识整合方法**\n\n**多学科知识融合**：\n- **知识迁移**：将一个学科的知识应用到另一个学科\n- **概念整合**：整合不同学科的核心概念\n- **方法借鉴**：借鉴其他学科的研究方法\n\n**整合策略**：\n- **主题整合**：围绕共同主题整合多学科知识\n- **问题整合**：为解决具体问题整合相关知识\n- **项目整合**：在项目实施中整合多学科资源\n\n#### **2. 多视角分析方法**\n\n**视角转换技巧**：\n- **角色转换**：从不同角色的角度分析问题\n- **时间转换**：从不同时间尺度分析问题\n- **空间转换**：从不同空间尺度分析问题\n\n**多视角综合**：\n- **视角对比**：比较不同视角的分析结果\n- **视角互补**：用不同视角补充完善认识\n- **视角整合**：整合多个视角形成全面认识\n\n#### **3. 创新思维方法**\n\n**跨界创新策略**：\n- **类比创新**：从其他领域寻找解决方案\n- **组合创新**：组合不同学科的元素创新\n- **移植创新**：将一个领域的方法移植到另一个领域\n\n**创新思维培养**：\n- **好奇心培养**：对不同领域保持好奇心\n- **开放性思维**：接受不同学科的观点和方法\n- **批判性思维**：批判性地评估跨学科的结合\n\n### 🛠️ 系统世界观的应用策略\n\n#### **在学习中的应用**\n\n**学科整合学习**：\n- **主题学习**：围绕主题整合多学科内容\n- **项目学习**：通过项目实践整合知识技能\n- **问题学习**：通过解决问题整合多学科知识\n\n**知识结构建构**：\n- **概念地图**：构建跨学科的概念关系图\n- **知识网络**：建立学科间的知识连接\n- **思维模型**：形成跨学科的思维模型\n\n#### **在生活中的应用**\n\n**复杂问题解决**：\n- **多角度分析**：从多个角度分析生活问题\n- **系统性解决**：设计系统性的解决方案\n- **整体性规划**：进行整体性的人生规划\n\n**决策制定**：\n- **多因素考虑**：考虑决策的多方面影响\n- **长远规划**：从长远角度制定决策\n- **系统优化**：优化个人和家庭系统\n\n#### **在未来发展中的应用**\n\n**职业发展**：\n- **跨界能力**：培养跨领域的综合能力\n- **创新思维**：具备跨学科创新思维\n- **适应能力**：适应跨学科合作的工作环境\n\n**社会参与**：\n- **公民素养**：具备系统性的公民素养\n- **社会责任**：承担系统性的社会责任\n- **全球视野**：具备全球系统的视野格局\n\n---",
      "subsections": [
        {
          "id": "-",
          "title": "🎯 系统世界观的核心要素",
          "type": "content",
          "content": ""
        },
        {
          "id": "-",
          "title": "🔄 跨学科思维的实践方法",
          "type": "method",
          "content": ""
        },
        {
          "id": "-",
          "title": "🛠️ 系统世界观的应用策略",
          "type": "content",
          "content": ""
        }
      ]
    },
    {
      "id": "-",
      "title": "🛠️ 实用工具：系统世界观分析框架",
      "type": "general",
      "content": "```\n系统世界观分析框架\n\n第一部分：整体性分析\n分析对象：_______\n整体目标：_______\n主要组成部分：\n1. _______\n2. _______\n3. _______\n整体特性（部分所没有的）：_______\n\n第二部分：关联性分析\n内部关联：\n要素A ←→ 要素B：_______\n要素B ←→ 要素C：_______\n要素C ←→ 要素A：_______\n\n外部关联：\n与环境因素1的关系：_______\n与环境因素2的关系：_______\n与环境因素3的关系：_______\n\n第三部分：层次性分析\n上层系统：_______\n本层系统：_______\n下层系统：_______\n\n跨层次影响：\n上层对本层的影响：_______\n本层对下层的影响：_______\n下层对上层的影响：_______\n\n第四部分：动态性分析\n历史发展：_______\n现状特征：_______\n发展趋势：_______\n关键变化因素：_______\n\n第五部分：跨学科视角\n相关学科1：_______（提供的视角：_______）\n相关学科2：_______（提供的视角：_______）\n相关学科3：_______（提供的视角：_______）\n\n跨学科整合洞察：_______\n\n第六部分：应用启示\n对理解问题的启示：_______\n对解决问题的启示：_______\n对未来发展的启示：_______\n```\n\n---",
      "subsections": []
    },
    {
      "id": "-5",
      "title": "🎮 交互练习（5分钟）",
      "type": "interactive-exercise",
      "content": "### 🎯 练习1：系统世界观应用\n用系统世界观分析下面的现象：\n\n**现象**：城市交通拥堵问题\n\n**整体性分析**：\n- 这个问题涉及哪些主要系统？_______\n- 整体目标是什么？_______\n\n**关联性分析**：\n- 列出3个相互关联的因素：_______\n\n**层次性分析**：\n- 个人层次的因素：_______\n- 社会层次的因素：_______\n- 政策层次的因素：_______\n\n**动态性分析**：\n- 这个问题的发展趋势：_______\n\n### 🎯 练习2：跨学科思维训练\n为下面的问题设计跨学科分析方案：\n\n**问题**：如何提高学生的学习兴趣？\n\n**相关学科及其贡献**：\n1. 心理学：_______\n2. 教育学：_______\n3. 神经科学：_______\n4. 社会学：_______\n5. 技术学：_______\n\n**跨学科整合方案**：_______\n\n### 🎯 练习3：系统思维实践\n选择一个你关心的问题，用系统世界观分析框架进行完整分析：\n\n**你选择的问题**：_______\n**分析结果**：（使用上面的分析框架）\n\n✍️ **动手记录**：在日常生活中寻找一个可以用系统世界观分析的现象，并尝试从多个学科角度理解它。\n\n---",
      "subsections": [
        {
          "id": "-1",
          "title": "🎯 练习1：系统世界观应用",
          "type": "exercise",
          "content": ""
        },
        {
          "id": "-2",
          "title": "🎯 练习2：跨学科思维训练",
          "type": "exercise",
          "content": ""
        },
        {
          "id": "-3",
          "title": "🎯 练习3：系统思维实践",
          "type": "exercise",
          "content": ""
        }
      ]
    },
    {
      "id": "-2",
      "title": "✅ 技能确认测试（2分钟）",
      "type": "skill-test",
      "content": "### 🧪 快速测试\n\n**情况**：某地区出现了\"留守儿童教育问题\"，当地政府希望制定综合解决方案。\n\n**问题**：运用系统世界观和跨学科思维，应该如何分析这个问题？\n\nA. 主要从教育学角度分析，重点改善学校教育质量\nB. 从经济学角度分析，主要解决家庭经济问题\nC. 运用系统思维整体分析，整合教育学、心理学、社会学、经济学等多学科视角，设计综合解决方案\nD. 分别从各个学科角度独立分析，然后简单相加\n\n**正确答案**：C\n**解释**：留守儿童教育问题是一个复杂的系统性问题，涉及教育、心理、社会、经济、政策等多个层面。需要运用系统世界观从整体性、关联性、层次性、动态性角度分析，同时运用跨学科思维整合多个学科的知识和方法，设计系统性的综合解决方案。单一学科视角或简单相加都无法有效解决这类复杂问题。\n\n### ✨ 技能确认\n\n如果你能运用系统世界观分析复杂现象，掌握跨学科思维方法，形成整体性、关联性、动态性的认知习惯，恭喜你建立了系统化的世界观！\n\n---",
      "subsections": [
        {
          "id": "-",
          "title": "🧪 快速测试",
          "type": "exercise",
          "content": ""
        },
        {
          "id": "-",
          "title": "✨ 技能确认",
          "type": "content",
          "content": ""
        }
      ]
    },
    {
      "id": "-",
      "title": "📚 课程小结",
      "type": "summary",
      "content": "**今天你学会了**：\n- ✅ 理解系统世界观：整体性、关联性、层次性、动态性的认知方式\n- ✅ 掌握跨学科思维：整合多学科知识和方法解决复杂问题\n- ✅ 学会系统分析：用系统视角分析复杂现象和问题\n- ✅ 建立思维习惯：形成系统化的思维方式和认知习惯\n\n**重要收获**：\n系统化的世界观和跨学科思维能力。这是21世纪最重要的思维能力之一，它将帮助你更好地理解复杂世界，解决复杂问题，适应未来发展。\n\n**系统思维基础模块完成**：\n恭喜你完成了系统思维基础模块的全部学习！你已经掌握了系统思维的核心概念和方法，建立了系统化的世界观。\n\n---",
      "subsections": []
    },
    {
      "id": "-8",
      "title": "💡 深度拓展：成人世界的系统世界观智慧（8分钟）",
      "type": "deep-extension",
      "content": "### 🌍 21世纪的跨学科革命\n\n在成人世界里，系统世界观和跨学科思维正在重塑各个领域：\n\n#### **案例1：现代医学的系统性变革**\n\n**传统医学模式的局限**：\n- **分科治疗**：内科、外科、妇科等各自独立\n- **症状导向**：头痛医头，脚痛医脚\n- **单一病因**：寻找疾病的单一原因\n- **标准化治疗**：所有患者使用相同治疗方案\n\n**系统医学的新范式**：\n\n**整体性医疗**：\n- **全人医疗**：将患者视为生物-心理-社会的整体\n- **系统诊断**：分析疾病在整个身体系统中的表现\n- **预防为主**：从系统角度预防疾病发生\n\n**跨学科整合**：\n- **生物医学+信息技术**：精准医疗、基因治疗\n- **医学+心理学**：心身医学、行为医学\n- **医学+工程学**：医疗器械、人工器官\n- **医学+数据科学**：医疗大数据、AI诊断\n- **医学+社会学**：公共卫生、健康管理\n\n**系统性治疗方案**：\n\n**慢性病管理的系统方法**：\n- **生物层面**：药物治疗、手术干预\n- **心理层面**：心理支持、认知调整\n- **行为层面**：生活方式改变、习惯培养\n- **社会层面**：家庭支持、社区资源\n- **环境层面**：环境改善、职业调整\n\n**效果**：\n- 治疗效果显著提升\n- 患者满意度大幅改善\n- 医疗成本有效控制\n- 医疗资源优化配置\n\n#### **案例2：现代企业管理的系统性思维**\n\n**传统管理模式**：\n- **职能分割**：各部门独立运作\n- **层级管理**：严格的等级制度\n- **效率导向**：只关注生产效率\n- **短期目标**：季度和年度业绩\n\n**系统性管理的新模式**：\n\n**整体性组织设计**：\n- **扁平化结构**：减少管理层级，提高响应速度\n- **跨职能团队**：打破部门壁垒，促进协作\n- **生态系统思维**：将企业视为商业生态系统的一部分\n\n**跨学科管理方法**：\n- **管理学+心理学**：员工激励、团队建设\n- **管理学+数据科学**：商业智能、决策支持\n- **管理学+设计学**：用户体验、产品创新\n- **管理学+生态学**：可持续发展、循环经济\n- **管理学+复杂科学**：组织演化、适应性管理\n\n**系统性绩效管理**：\n\n**平衡计分卡方法**：\n- **财务维度**：收入、利润、成本控制\n- **客户维度**：满意度、忠诚度、市场份额\n- **内部流程维度**：效率、质量、创新\n- **学习成长维度**：员工能力、组织文化\n\n**效果**：\n- 组织适应性显著增强\n- 创新能力大幅提升\n- 员工满意度持续改善\n- 可持续发展能力增强\n\n#### **案例3：城市规划的系统性革命**\n\n**传统城市规划**：\n- **功能分区**：居住区、商业区、工业区严格分离\n- **交通导向**：以汽车交通为主导\n- **经济优先**：主要考虑经济发展需求\n- **静态规划**：制定固定的长期规划\n\n**系统性城市规划**：\n\n**整体性城市设计**：\n- **混合功能**：居住、工作、娱乐、教育混合布局\n- **多元交通**：步行、自行车、公交、汽车协调发展\n- **生态优先**：将生态系统纳入城市规划\n- **韧性城市**：提高城市应对各种冲击的能力\n\n**跨学科规划方法**：\n- **城市规划+生态学**：生态城市、绿色基础设施\n- **城市规划+社会学**：社区营造、社会公平\n- **城市规划+经济学**：产城融合、经济可持续\n- **城市规划+技术学**：智慧城市、数字化治理\n- **城市规划+心理学**：宜居环境、人性化设计\n\n**系统性城市治理**：\n\n**多层次治理体系**：\n- **政府层面**：政策制定、资源配置\n- **市场层面**：市场机制、企业参与\n- **社会层面**：公众参与、社区自治\n- **技术层面**：智能系统、数据驱动\n\n**效果**：\n- 城市生活质量显著提升\n- 环境可持续性大幅改善\n- 社会公平性持续增强\n- 经济活力不断增长\n\n### 🌟 系统世界观的前沿应用\n\n#### **1. 人工智能与系统思维**\n- **多模态AI**：整合视觉、听觉、语言等多种信息\n- **强化学习**：在复杂环境中学习最优策略\n- **群体智能**：模拟生物群体的集体智慧\n\n#### **2. 可持续发展与系统方法**\n- **循环经济**：构建闭环的经济系统\n- **碳中和**：系统性减少温室气体排放\n- **生态文明**：人与自然和谐共生的系统\n\n#### **3. 全球治理与系统协调**\n- **多边合作**：在全球层面协调各国行动\n- **跨国问题**：系统性解决全球性挑战\n- **人类命运共同体**：构建全人类的共同系统\n\n### 🌟 成年人的系统世界观实践\n\n#### **在职业发展中**：\n- **跨界能力**：培养跨行业、跨职能的综合能力\n- **系统思维**：从系统角度规划职业发展路径\n- **终身学习**：建立跨学科的知识体系\n\n#### **在创新创业中**：\n- **商业生态**：构建完整的商业生态系统\n- **跨界创新**：在学科交叉点寻找创新机会\n- **系统解决方案**：提供系统性的产品和服务\n\n#### **在社会参与中**：\n- **公民责任**：从系统角度承担社会责任\n- **全球视野**：具备全球系统的思维格局\n- **可持续生活**：践行可持续的生活方式\n\n#### **在个人成长中**：\n- **全面发展**：身心灵的系统性发展\n- **关系网络**：构建健康的人际关系系统\n- **生活平衡**：在工作、家庭、健康间保持平衡\n\n记住，系统世界观不仅是一种思维方式，更是一种生活方式和价值观。在这个日益复杂和相互依存的世界里，只有具备系统思维的人才能真正理解世界的本质，找到自己的位置，创造有意义的人生。\n\n---",
      "subsections": [
        {
          "id": "-21",
          "title": "🌍 21世纪的跨学科革命",
          "type": "content",
          "content": ""
        },
        {
          "id": "-",
          "title": "🌟 系统世界观的前沿应用",
          "type": "content",
          "content": ""
        },
        {
          "id": "-",
          "title": "🌟 成年人的系统世界观实践",
          "type": "content",
          "content": ""
        }
      ]
    },
    {
      "id": "-",
      "title": "🏠 生活应用提示",
      "type": "life-application",
      "content": "### 今天就可以尝试：\n1. **系统观察**：选择一个身边的现象，尝试从系统角度分析\n2. **跨学科思考**：在学习或工作中，尝试运用其他学科的知识\n3. **整体规划**：从系统角度规划自己的一天或一周\n\n### 明天的小挑战：\n选择一个你关心的社会问题，运用系统世界观分析框架进行完整分析，并思考可能的跨学科解决方案。\n\n### 🎓 系统思维基础模块学习成果\n\n通过系统思维基础模块的学习，你已经：\n- ✅ 掌握了系统思维的核心概念和方法\n- ✅ 学会了分析复杂系统的基本技能\n- ✅ 建立了系统化的世界观和思维习惯\n- ✅ 具备了跨学科思维的基础能力\n\n这些能力将成为你未来学习和发展的重要基础，帮助你在复杂的世界中保持清晰的思维，做出明智的决策，创造有价值的人生！",
      "subsections": [
        {
          "id": "-",
          "title": "今天就可以尝试：",
          "type": "content",
          "content": ""
        },
        {
          "id": "-",
          "title": "明天的小挑战：",
          "type": "content",
          "content": ""
        },
        {
          "id": "-",
          "title": "🎓 系统思维基础模块学习成果",
          "type": "content",
          "content": ""
        }
      ]
    }
  ],
  "metadata": {
    "convertedAt": "2025-07-01T05:30:09.455Z",
    "originalFile": "第74课-系统世界观与跨学科思维-系统思维基础.md"
  },
  "moduleDir": "03-基础模块",
  "moduleName": "基础模块"
}