{
  "id": 68,
  "filename": "第68课-系统的限制因素与杠杆点-系统思维基础.md",
  "title": "第66课：系统的限制因素与杠杆点（用小力量撬动大变化）",
  "module": "系统思维基础",
  "grade": "4年级及以上（已完成入门阶段学习）",
  "duration": "",
  "objective": "",
  "sections": [
    {
      "id": "-",
      "title": "📚 课程信息",
      "type": "general",
      "content": "- **学习时长**：23分钟（技能掌握15分钟 + 深度拓展8分钟）\n- **核心技能**：识别系统中的限制因素和杠杆点，学会用最小的努力产生最大的改变\n\n---",
      "subsections": []
    },
    {
      "id": "-",
      "title": "🎯 学习目标",
      "type": "general",
      "content": "学完这节课，你将能够：\n- ✅ 理解限制因素（瓶颈）的概念和影响\n- ✅ 识别系统中的杠杆点\n- ✅ 分析限制因素如何影响系统整体表现\n- ✅ 学会寻找和利用杠杆点进行系统改进\n\n---",
      "subsections": []
    },
    {
      "id": "-3",
      "title": "📖 概念导入（3分钟）",
      "type": "introduction",
      "content": "### 🤔 思考一下\n\n在日常生活中，我们经常遇到这样的现象：\n\n**学习中的瓶颈**：\n- 小明各科成绩都不错，但数学总是拖后腿，影响了总成绩\n- 小红背单词很快，但听力不好，英语整体水平提不上去\n- 班级整体学习氛围很好，但几个调皮的同学总是影响课堂纪律\n\n**生活中的限制**：\n- 家里网速很快，但路由器老旧，导致网络经常卡顿\n- 一个水桶有几块木板很高，但有一块很短，水总是从短板处溢出\n- 食堂有很多窗口，但收银台只有一个，导致排队时间很长\n\n**小改变大影响**：\n- 班长换了一个更负责任的人，整个班级的纪律都改善了\n- 在关键路口增加了一个红绿灯，整条路的交通都顺畅了\n- 老师改变了一个教学方法，全班同学的学习兴趣都提高了\n\n你有没有发现：有时候系统中的一个小问题会影响整体表现，而解决一个关键问题就能带来巨大改善？\n\n### 💡 核心概念\n\n#### **什么是限制因素（瓶颈）？**\n\n**限制因素的定义**：\n- **基本含义**：系统中限制整体表现的关键环节或因素\n- **核心特征**：决定系统整体能力的最薄弱环节\n- **重要作用**：找到限制因素是改进系统的关键\n\n**限制因素的特点**：\n1. **决定性影响**：限制因素决定系统的整体表现\n2. **相对性**：在不同情况下，限制因素可能不同\n3. **动态性**：解决一个限制因素后，可能出现新的限制因素\n4. **系统性**：限制因素往往与系统结构有关\n\n#### **什么是杠杆点？**\n\n**杠杆点的定义**：\n- **基本含义**：系统中能够用较小的努力产生较大改变的关键点\n- **核心特征**：四两拨千斤的作用点\n- **重要作用**：找到杠杆点可以高效地改进系统\n\n**杠杆点的特点**：\n1. **高效性**：小的投入带来大的产出\n2. **战略性**：影响系统的关键结构或流程\n3. **持久性**：改变往往具有持续的影响\n4. **系统性**：影响系统的多个方面\n\n#### **限制因素与杠杆点的关系**\n\n**相互关系**：\n- **限制因素往往是杠杆点**：解决限制因素通常能带来显著改善\n- **杠杆点不一定是限制因素**：有些杠杆点是创造新机会的点\n- **动态转换**：解决限制因素后，新的杠杆点可能出现\n\n**木桶理论的启示**：\n- **短板决定容量**：最短的木板决定水桶的容量\n- **补短板效应**：加高最短的木板能最有效地增加容量\n- **新短板出现**：补高一块短板后，其他板可能成为新的短板\n\n#### **寻找限制因素和杠杆点的方法**\n\n**观察法**：\n- 观察系统运行过程中的瓶颈\n- 找出经常出现问题的环节\n- 识别影响整体效率的因素\n\n**分析法**：\n- 分析系统的流程和结构\n- 计算各环节的处理能力\n- 找出能力最弱的环节\n\n**实验法**：\n- 尝试改变不同的因素\n- 观察哪些改变带来最大效果\n- 通过试错找到关键点\n\n**询问法**：\n- 询问系统中的参与者\n- 了解他们认为的主要问题\n- 收集改进建议\n\n---",
      "subsections": [
        {
          "id": "-",
          "title": "🤔 思考一下",
          "type": "reflection",
          "content": ""
        },
        {
          "id": "-",
          "title": "💡 核心概念",
          "type": "content",
          "content": ""
        }
      ]
    },
    {
      "id": "-5",
      "title": "🎬 案例展示（5分钟）",
      "type": "case-study",
      "content": "### 📚 案例1：学习效率提升的限制因素分析\n\n**背景**：小李想提高自己的学习效率，但尝试了很多方法效果都不明显\n\n**系统分析**：\n\n**学习系统的组成要素**：\n- **时间管理**：学习时间的安排和利用\n- **学习环境**：学习场所的安静程度和设施\n- **学习方法**：记忆、理解、练习的方法\n- **身体状态**：精力、健康、作息规律\n- **心理状态**：动机、专注力、情绪管理\n\n**限制因素识别过程**：\n\n**第一步：现状调查**\n- **时间管理**：每天学习6小时，时间充足\n- **学习环境**：房间安静，设施齐全\n- **学习方法**：主要是反复阅读和背诵\n- **身体状态**：经常熬夜，白天精力不足\n- **心理状态**：容易分心，注意力难以集中\n\n**第二步：瓶颈分析**\n通过观察和记录，发现：\n- 学习时间虽长，但有效学习时间很短\n- 经常看书看着看着就走神了\n- 记忆效果差，学过的内容容易忘记\n- 身体疲劳时学习效率极低\n\n**第三步：限制因素确定**\n**主要限制因素**：注意力不集中\n- **影响程度**：直接影响学习效率和记忆效果\n- **连锁反应**：导致学习时间延长，身体更疲劳，形成恶性循环\n\n**第四步：杠杆点识别**\n**关键杠杆点**：改善专注力\n- **具体措施**：\n  - 使用番茄工作法，25分钟专注学习+5分钟休息\n  - 学习前进行5分钟冥想，提高专注力\n  - 关闭手机和其他干扰源\n  - 保证充足睡眠，提高白天精力\n\n**第五步：效果验证**\n实施改进措施后：\n- **专注时间**：从平均10分钟提高到25分钟\n- **学习效率**：同样内容的学习时间减少40%\n- **记忆效果**：记忆保持率提高60%\n- **整体感受**：学习压力减少，成就感增强\n\n**案例启示**：\n- **找对关键点很重要**：专注力是学习系统的核心限制因素\n- **系统性改善**：改善一个关键因素带动整个系统改善\n- **持续监控**：需要持续观察是否出现新的限制因素\n\n### 🏃 案例2：食堂排队系统的瓶颈分析\n\n**背景**：学校食堂午餐时间排队过长，学生抱怨很多\n\n**系统流程分析**：\n\n**食堂服务流程**：\n```\n学生到达 → 排队等候 → 选择菜品 → 打菜装盘 → 结账付款 → 找座就餐\n```\n\n**各环节能力分析**：\n- **排队等候**：空间充足，可容纳200人排队\n- **选择菜品**：菜品丰富，选择时间平均30秒\n- **打菜装盘**：6个窗口，每个窗口平均服务时间2分钟\n- **结账付款**：2个收银台，每次结账平均30秒\n- **找座就餐**：300个座位，翻台率较高\n\n**瓶颈识别**：\n\n**数据收集**：\n- **高峰期人流**：12:00-12:30，约600人就餐\n- **各环节处理能力**：\n  - 打菜窗口：6个×30人/小时 = 180人/小时\n  - 收银台：2个×120人/小时 = 240人/小时\n  - 座位：300个×2次翻台 = 600人/小时\n\n**瓶颈分析**：\n**主要瓶颈**：打菜窗口\n- **处理能力**：180人/小时\n- **需求量**：600人/30分钟 = 1200人/小时\n- **缺口**：1200 - 180 = 1020人/小时\n\n**杠杆点设计**：\n\n**方案A：增加打菜窗口**\n- **投入**：增加2个窗口，需要额外人员和设备\n- **效果**：处理能力提升到240人/小时\n- **问题**：仍然不够，且成本较高\n\n**方案B：优化打菜流程**\n- **预装盒饭**：提前准备50%的标准套餐\n- **分类窗口**：套餐窗口和自选窗口分开\n- **效果**：套餐窗口服务时间减少到30秒，处理能力翻倍\n\n**方案C：错峰就餐**\n- **时间引导**：鼓励不同年级错峰就餐\n- **激励机制**：非高峰期就餐给予小优惠\n- **效果**：分散高峰期压力\n\n**最终方案**：组合策略\n- **短期**：实施方案B，优化打菜流程\n- **中期**：实施方案C，引导错峰就餐\n- **长期**：根据效果考虑是否增加窗口\n\n**实施效果**：\n- **排队时间**：从平均15分钟减少到5分钟\n- **学生满意度**：显著提升\n- **成本投入**：相对较低\n\n### 🌱 案例3：班级学习氛围改善的杠杆点\n\n**背景**：某班级学习氛围不够浓厚，同学们学习积极性不高\n\n**系统要素分析**：\n\n**影响学习氛围的因素**：\n- **班级文化**：是否重视学习，是否有学习传统\n- **同伴影响**：同学之间是否相互鼓励学习\n- **老师引导**：老师是否积极引导和激励\n- **环境设置**：教室布置是否有利于学习\n- **制度安排**：是否有促进学习的制度和活动\n\n**现状调查**：\n- **班级文化**：比较重视娱乐，对学习重视不够\n- **同伴影响**：学习好的同学比较孤立，影响力有限\n- **老师引导**：老师很努力，但效果不明显\n- **环境设置**：教室布置普通，缺乏学习氛围\n- **制度安排**：缺乏有效的学习激励机制\n\n**杠杆点识别**：\n\n**分析各因素的影响力**：\n- **班级文化**：影响深远但改变困难\n- **同伴影响**：影响直接且容易改变\n- **老师引导**：重要但已经在做\n- **环境设置**：影响有限\n- **制度安排**：可以设计但需要持续执行\n\n**关键杠杆点**：同伴影响\n- **原因分析**：同龄人的影响力往往比成年人更大\n- **改变可能性**：相对容易通过活动和引导改变\n- **影响范围**：能够影响整个班级的氛围\n\n**杠杆点干预策略**：\n\n**策略1：学习榜样塑造**\n- **发现榜样**：找出班级中学习认真且受欢迎的同学\n- **榜样展示**：让榜样分享学习经验和心得\n- **榜样带动**：鼓励榜样主动帮助其他同学\n\n**策略2：学习小组建设**\n- **混合分组**：学习好的和学习一般的同学混合分组\n- **小组竞赛**：开展小组间的学习竞赛活动\n- **互助机制**：建立小组内的互助学习机制\n\n**策略3：学习成果展示**\n- **成果分享**：定期让同学分享学习收获\n- **进步表彰**：表彰学习进步明显的同学\n- **集体荣誉**：将个人学习与班级荣誉联系起来\n\n**实施效果**：\n- **学习氛围**：班级学习氛围明显改善\n- **同伴关系**：学习好的同学不再孤立\n- **整体成绩**：班级平均成绩有所提升\n- **持续性**：形成了良性循环，效果持续\n\n**🔍 思考**：为什么找到限制因素和杠杆点如此重要？在改进系统时，我们应该优先关注什么？如何避免\"头痛医头，脚痛医脚\"的问题？\n\n---",
      "subsections": [
        {
          "id": "-1",
          "title": "📚 案例1：学习效率提升的限制因素分析",
          "type": "case",
          "content": ""
        },
        {
          "id": "-2",
          "title": "🏃 案例2：食堂排队系统的瓶颈分析",
          "type": "case",
          "content": ""
        },
        {
          "id": "-3",
          "title": "🌱 案例3：班级学习氛围改善的杠杆点",
          "type": "case",
          "content": ""
        }
      ]
    },
    {
      "id": "-5",
      "title": "🧠 核心内容（5分钟）",
      "type": "core-content",
      "content": "### 🎯 系统性寻找限制因素的方法\n\n#### **流程分析法**\n\n**1. 绘制系统流程图**\n- **识别关键步骤**：列出系统运行的主要步骤\n- **标注处理能力**：记录每个步骤的处理能力或速度\n- **计算总体能力**：找出处理能力最低的环节\n\n**例子：作业完成流程**\n```\n理解题目(5分钟) → 查找资料(15分钟) → 思考解答(20分钟) → \n书写答案(10分钟) → 检查修改(10分钟)\n```\n**瓶颈**：思考解答环节时间最长，是主要限制因素\n\n**2. 数据收集与分析**\n- **量化各环节**：用数据衡量各环节的表现\n- **找出差距**：比较各环节的能力差异\n- **验证假设**：通过数据验证限制因素的判断\n\n#### **问题追踪法**\n\n**1. 问题频发点识别**\n- **记录问题**：记录系统运行中经常出现的问题\n- **分析模式**：找出问题出现的规律和模式\n- **追溯根源**：从问题现象追溯到根本原因\n\n**2. 影响传播分析**\n- **影响链条**：分析一个问题如何影响其他环节\n- **放大效应**：找出能够放大问题影响的因素\n- **关键节点**：识别影响传播的关键节点\n\n#### **资源约束分析**\n\n**1. 资源盘点**\n- **人力资源**：分析人员的数量、能力、时间分配\n- **物质资源**：分析设备、材料、空间等资源\n- **信息资源**：分析信息的获取、处理、传递能力\n\n**2. 约束识别**\n- **绝对约束**：无法改变的硬性限制\n- **相对约束**：可以通过努力改善的限制\n- **隐性约束**：不容易发现但影响很大的限制\n\n### 🔍 杠杆点的层次和类型\n\n#### **杠杆点的层次（从低到高）**\n\n**第一层：参数调整**\n- **特点**：改变系统中的数量、大小、速度等参数\n- **效果**：影响有限，但容易实施\n- **例子**：增加学习时间、提高工作效率\n\n**第二层：物质结构**\n- **特点**：改变系统的物理结构或组织结构\n- **效果**：影响较大，需要一定投入\n- **例子**：重新安排座位、调整组织架构\n\n**第三层：规则制度**\n- **特点**：改变系统运行的规则和制度\n- **效果**：影响深远，但可能遇到阻力\n- **例子**：修改考核制度、建立新的流程\n\n**第四层：权力分配**\n- **特点**：改变系统中的权力和决策结构\n- **效果**：根本性影响，但改变困难\n- **例子**：改变决策机制、重新分配权力\n\n**第五层：目标导向**\n- **特点**：改变系统的目标和价值观\n- **效果**：最根本的改变，但需要长期努力\n- **例子**：改变组织文化、重新定义成功标准\n\n#### **杠杆点的类型**\n\n**1. 结构性杠杆点**\n- **定义**：改变系统结构的关键点\n- **特点**：影响系统的基本运作方式\n- **例子**：改变组织结构、调整流程设计\n\n**2. 信息性杠杆点**\n- **定义**：改变信息流动的关键点\n- **特点**：通过信息改变行为和决策\n- **例子**：建立反馈机制、提供关键信息\n\n**3. 激励性杠杆点**\n- **定义**：改变激励机制的关键点\n- **特点**：通过改变动机影响行为\n- **例子**：调整奖惩制度、重新设计激励\n\n**4. 能力性杠杆点**\n- **定义**：提升关键能力的关键点\n- **特点**：通过能力提升改善整体表现\n- **例子**：培训关键人员、引入新技术\n\n### 🛠️ 实用工具：限制因素与杠杆点分析表\n\n```\n限制因素与杠杆点分析表\n\n第一部分：系统基本信息\n系统名称：_______\n分析目标：_______\n当前主要问题：_______\n\n第二部分：系统要素分析\n关键要素1：_______\n处理能力：_______\n关键要素2：_______\n处理能力：_______\n关键要素3：_______\n处理能力：_______\n\n第三部分：限制因素识别\n方法：□流程分析 □问题追踪 □资源约束分析\n主要限制因素：_______\n限制程度：□严重 □中等 □轻微\n影响范围：_______\n产生原因：_______\n\n第四部分：杠杆点识别\n潜在杠杆点1：_______\n影响程度：□高 □中 □低\n实施难度：□易 □中 □难\n潜在杠杆点2：_______\n影响程度：□高 □中 □低\n实施难度：□易 □中 □难\n\n第五部分：优先级排序\n最重要的限制因素：_______\n最有效的杠杆点：_______\n优先改进顺序：\n1. _______\n2. _______\n3. _______\n\n第六部分：行动计划\n具体改进措施：_______\n预期效果：_______\n实施时间：_______\n监控指标：_______\n```\n\n---",
      "subsections": [
        {
          "id": "-",
          "title": "🎯 系统性寻找限制因素的方法",
          "type": "method",
          "content": ""
        },
        {
          "id": "-",
          "title": "🔍 杠杆点的层次和类型",
          "type": "content",
          "content": ""
        },
        {
          "id": "-",
          "title": "🛠️ 实用工具：限制因素与杠杆点分析表",
          "type": "content",
          "content": ""
        }
      ]
    },
    {
      "id": "-5",
      "title": "🎮 交互练习（5分钟）",
      "type": "interactive-exercise",
      "content": "### 🎯 练习1：限制因素识别\n分析下面系统的限制因素：\n\n**系统A：班级卫生管理**\n**现状**：班级卫生评分总是不高，主要问题是地面不够干净\n\n**系统要素**：\n- 扫地：每天有人负责扫地\n- 拖地：每天有人负责拖地  \n- 垃圾清理：每天有人负责倒垃圾\n- 桌椅整理：每天有人负责整理桌椅\n- 监督检查：班长负责检查\n\n**分析任务**：\n- 可能的限制因素：_______\n- 判断依据：_______\n- 改进建议：_______\n\n### 🎯 练习2：杠杆点设计\n为下面的情况设计杠杆点：\n\n**情况**：班级同学参与课堂讨论的积极性不高\n\n**现状分析**：\n- 老师经常提问，但主动回答的同学很少\n- 大部分同学担心回答错误被笑话\n- 课堂气氛比较沉闷\n- 老师希望提高课堂互动性\n\n**杠杆点设计**：\n- 杠杆点1：_______\n- 实施方法：_______\n- 预期效果：_______\n\n### 🎯 练习3：系统改进方案\n设计一个系统改进方案：\n\n**系统**：个人时间管理\n\n**当前问题**：\n- 经常感觉时间不够用\n- 重要的事情总是被拖延\n- 学习和娱乐时间分配不合理\n\n**分析任务**：\n- 主要限制因素：_______\n- 关键杠杆点：_______\n- 具体改进措施：_______\n- 预期改进效果：_______\n\n✍️ **动手记录**：用限制因素与杠杆点分析表分析一个你想要改进的系统。\n\n---",
      "subsections": [
        {
          "id": "-1",
          "title": "🎯 练习1：限制因素识别",
          "type": "exercise",
          "content": ""
        },
        {
          "id": "-2",
          "title": "🎯 练习2：杠杆点设计",
          "type": "exercise",
          "content": ""
        },
        {
          "id": "-3",
          "title": "🎯 练习3：系统改进方案",
          "type": "exercise",
          "content": ""
        }
      ]
    },
    {
      "id": "-2",
      "title": "✅ 技能确认测试（2分钟）",
      "type": "skill-test",
      "content": "### 🧪 快速测试\n\n**情况**：某学习小组的学习效果不理想。经过观察发现：小组有6个人，其中4个人都很认真，但有2个人经常不参与讨论，也不认真完成任务，影响了整个小组的学习氛围和效果。\n\n**问题**：从限制因素和杠杆点的角度，应该如何改进这个学习小组？\n\nA. 增加更多认真的成员，稀释不认真成员的影响\nB. 重点关注和改善那2个不认真成员的参与度\nC. 让4个认真的成员单独组成新的学习小组\nD. 制定更严格的规则来约束所有成员\n\n**正确答案**：B\n**解释**：在这个学习小组系统中，那2个不认真的成员是明显的限制因素，他们的消极态度限制了整个小组的学习效果。根据木桶理论，系统的整体表现往往受最薄弱环节的限制。因此，改善这2个成员的参与度是最有效的杠杆点，能够用相对较小的努力（针对2个人而不是6个人）产生较大的改变（提升整个小组的效果）。选项A成本太高，选项C破坏了小组完整性，选项D没有针对性地解决核心问题。\n\n### ✨ 技能确认\n\n如果你能识别系统中的限制因素，找到有效的杠杆点，并能设计针对性的改进方案，恭喜你掌握了系统优化的基础技能！\n\n---",
      "subsections": [
        {
          "id": "-",
          "title": "🧪 快速测试",
          "type": "exercise",
          "content": ""
        },
        {
          "id": "-",
          "title": "✨ 技能确认",
          "type": "content",
          "content": ""
        }
      ]
    },
    {
      "id": "-8",
      "title": "💡 深度拓展：成人世界的杠杆点智慧（8分钟）",
      "type": "deep-extension",
      "content": "### 🌍 企业管理中的约束理论应用\n\n在成人世界里，识别限制因素和杠杆点是企业管理、战略规划、个人发展的核心技能：\n\n#### **案例1：制造企业的约束理论实践**\n\n**场景**：某汽车零部件制造企业的生产效率提升项目\n\n**生产系统分析**：\n```\n原料准备 → 机械加工 → 质量检测 → 表面处理 → 包装出货\n(200件/小时) (120件/小时) (180件/小时) (150件/小时) (300件/小时)\n```\n\n**约束识别**：机械加工（120件/小时）是瓶颈工序，限制整条生产线产能\n\n**杠杆点干预策略**：\n- **第一阶段**：设备优化、工艺改进，产能提升到140件/小时\n- **第二阶段**：设备升级、工序重组，产能提升到180件/小时\n- **第三阶段**：新瓶颈管理，质量检测成为新约束点\n\n**管理价值**：聚焦改进、系统思维、持续改进、投资回报最大化\n\n#### **案例2：服务业的客户体验杠杆点**\n\n**场景**：某连锁餐厅的客户满意度提升项目\n\n**关键约束识别**：等待上菜时间过长（满意度仅60%）\n\n**杠杆点设计**：\n- **厨房效率优化**：标准化操作、预制半成品、设备升级\n- **客户期望管理**：透明化信息、过程娱乐、进度反馈\n- **需求平滑**：错峰激励、预约系统、菜单优化\n\n**实施效果**：等待满意度从60%提升到85%，整体满意度提升10%，营业额增长15%\n\n### 🎭 个人发展中的杠杆点思维\n\n#### **案例3：职业发展的关键杠杆点**\n\n**场景**：某中层管理者的职业发展规划\n\n**限制因素分析**：人际关系能力（5/10）是主要约束，限制晋升机会和资源获取\n\n**杠杆点策略设计**：\n- **第一阶段**：内部关系建设（向上管理、横向协作、向下领导）\n- **第二阶段**：外部网络拓展（行业活动、专业社群、导师关系）\n- **第三阶段**：影响力建设（内容分享、演讲机会、媒体曝光）\n\n**杠杆效应**：职业机会增加、资源获取容易、个人品牌提升、薪资大幅增长\n\n#### **案例4：个人财务管理的杠杆点**\n\n**场景**：某年轻职场人士的财务状况改善\n\n**限制因素识别**：储蓄率偏低（16.7%）、投资知识缺乏、消费习惯不良\n\n**杠杆点策略**：\n- **核心杠杆点1**：提升储蓄率（支出优化+收入提升）\n- **核心杠杆点2**：投资理财能力（知识学习+实践应用）\n\n**实施效果**：储蓄率提升到35%，投资收益率从2%提升到8%，购房目标提前2年实现\n\n### 🌟 杠杆点思维的高级应用\n\n#### **1. 系统性杠杆点识别**\n- **多层次分析**：个人、团队、组织、行业多层次识别\n- **时间维度考虑**：短期、中期、长期杠杆点区分\n- **影响力评估**：评估影响范围和持续时间\n\n#### **2. 杠杆点的组合应用**\n- **协同效应**：多个杠杆点组合使用\n- **时序安排**：合理安排实施顺序\n- **资源配置**：在不同杠杆点间分配资源\n\n#### **3. 动态杠杆点管理**\n- **持续监控**：监控杠杆点有效性变化\n- **适时调整**：根据环境变化调整策略\n- **新杠杆点发现**：持续寻找新机会\n\n### 🌟 成年人的杠杆点智慧\n\n#### **在企业管理中**：\n- **约束理论应用**：识别和管理生产经营瓶颈\n- **组织变革**：找到推动变革的关键杠杆点\n- **战略执行**：识别战略实施的关键成功因素\n\n#### **在个人发展中**：\n- **能力建设**：识别最能提升个人价值的核心能力\n- **关系建设**：建设对职业发展最关键的人际关系\n- **时间管理**：找到最能提升效率的时间管理方法\n\n#### **在投资理财中**：\n- **资产配置**：找到最能影响投资回报的关键因素\n- **风险管理**：识别最需要防范的关键风险点\n- **财富增长**：找到最能加速财富积累的杠杆点\n\n记住，杠杆点思维的核心是用最小的努力产生最大的改变。掌握这种思维方式，你就能在复杂的世界中找到关键的突破点，实现高效的系统改进和个人发展。\n\n---",
      "subsections": [
        {
          "id": "-",
          "title": "🌍 企业管理中的约束理论应用",
          "type": "content",
          "content": ""
        },
        {
          "id": "-",
          "title": "🎭 个人发展中的杠杆点思维",
          "type": "content",
          "content": ""
        },
        {
          "id": "-",
          "title": "🌟 杠杆点思维的高级应用",
          "type": "content",
          "content": ""
        },
        {
          "id": "-",
          "title": "🌟 成年人的杠杆点智慧",
          "type": "content",
          "content": ""
        }
      ]
    },
    {
      "id": "-",
      "title": "🏠 生活应用提示",
      "type": "life-application",
      "content": "### 今天就可以尝试：\n1. **瓶颈观察**：找一个你经常参与的活动，观察其中的瓶颈环节\n2. **杠杆点思考**：想想在学习或生活中，哪些小改变可能带来大影响\n3. **优先级排序**：列出你想改进的几个方面，按照杠杆效应排序\n\n### 明天的小挑战：\n选择一个你想要改进的系统（如学习方法、时间管理等），用今天学到的方法找出其限制因素和杠杆点。\n\n---",
      "subsections": [
        {
          "id": "-",
          "title": "今天就可以尝试：",
          "type": "content",
          "content": ""
        },
        {
          "id": "-",
          "title": "明天的小挑战：",
          "type": "content",
          "content": ""
        }
      ]
    },
    {
      "id": "-",
      "title": "📚 课程小结",
      "type": "summary",
      "content": "**今天你学会了**：\n- ✅ 理解限制因素：系统中限制整体表现的关键瓶颈\n- ✅ 识别杠杆点：能够用小力量撬动大变化的关键点\n- ✅ 分析方法：流程分析、问题追踪、资源约束等分析方法\n- ✅ 应用策略：优先解决限制因素，善用杠杆点实现高效改进\n\n**重要收获**：\n高效改进的系统智慧。掌握限制因素和杠杆点的识别方法，你就能避免平均用力，找到关键突破点，用最小的努力实现最大的改变。\n\n**下节课预告**：\n下节课我们将学习\"系统的适应性与鲁棒性/脆弱性\"——探索系统应对变化和冲击的能力！\n\n---",
      "subsections": []
    },
    {
      "id": "-8",
      "title": "💡 深度拓展：成人世界的杠杆点智慧（8分钟）",
      "type": "deep-extension",
      "content": "### 🌍 企业管理中的约束理论应用\n\n在成人世界里，识别限制因素和杠杆点是企业管理、战略规划、个人发展的核心技能：\n\n#### **案例1：制造企业的约束理论实践**\n\n**场景**：某汽车零部件制造企业的生产效率提升项目\n\n**生产系统分析**：\n\n**生产流程与能力**：\n```\n原料准备 → 机械加工 → 质量检测 → 表面处理 → 包装出货\n(200件/小时) (120件/小时) (180件/小时) (150件/小时) (300件/小时)\n```\n\n**约束识别**：\n- **瓶颈工序**：机械加工（120件/小时）\n- **影响分析**：限制整条生产线的产能\n- **成本影响**：其他工序的产能浪费，整体效率低下\n\n**杠杆点干预策略**：\n\n**第一阶段：挖掘现有潜力**\n- **设备优化**：对机械加工设备进行精密调校\n- **工艺改进**：优化加工参数，减少换刀时间\n- **人员培训**：提升操作工的技能水平\n- **效果**：产能从120件/小时提升到140件/小时\n\n**第二阶段：系统性改进**\n- **设备升级**：引入更高效的加工设备\n- **工序重组**：将部分加工工序前移或后移\n- **质量前置**：在机械加工前增加预检，减少返工\n- **效果**：产能提升到180件/小时\n\n**第三阶段：新瓶颈管理**\n- **新约束**：质量检测成为新的瓶颈（180件/小时）\n- **持续改进**：对质量检测工序进行优化\n- **系统平衡**：确保各工序能力匹配\n\n**约束理论的管理价值**：\n- **聚焦改进**：集中资源解决最关键的问题\n- **系统思维**：避免局部优化导致的整体次优\n- **持续改进**：建立动态的约束识别和改进机制\n- **投资回报**：确保改进投资产生最大效益\n\n#### **案例2：服务业的客户体验杠杆点**\n\n**场景**：某连锁餐厅的客户满意度提升项目\n\n**客户体验系统分析**：\n\n**服务流程与痛点**：\n```\n到店等位 → 点餐下单 → 等待上菜 → 用餐体验 → 结账离店\n```\n\n**客户满意度调研结果**：\n- **到店等位**：满意度75%（等位时间长）\n- **点餐下单**：满意度85%（服务员态度好）\n- **等待上菜**：满意度60%（等待时间过长）\n- **用餐体验**：满意度90%（菜品质量好）\n- **结账离店**：满意度80%（结账速度一般）\n\n**关键约束识别**：\n- **主要痛点**：等待上菜时间过长\n- **影响程度**：直接影响整体满意度\n- **根本原因**：厨房出菜速度与点餐速度不匹配\n\n**杠杆点设计**：\n\n**策略1：厨房效率优化**\n- **标准化操作**：制定标准化的菜品制作流程\n- **预制半成品**：对部分菜品进行预制处理\n- **设备升级**：引入更高效的厨房设备\n- **人员配置**：根据客流高峰调整厨师排班\n\n**策略2：客户期望管理**\n- **透明化信息**：告知客户准确的等待时间\n- **过程娱乐**：在等待期间提供小食或娱乐\n- **进度反馈**：实时更新菜品制作进度\n\n**策略3：需求平滑**\n- **错峰激励**：非高峰期提供优惠\n- **预约系统**：允许客户提前预约和点餐\n- **菜单优化**：推广制作时间短的菜品\n\n**实施效果**：\n- **等待上菜满意度**：从60%提升到85%\n- **整体满意度**：从78%提升到88%\n- **客户复购率**：提升25%\n- **营业额增长**：同比增长15%\n\n### 🎭 个人发展中的杠杆点思维\n\n#### **案例3：职业发展的关键杠杆点**\n\n**场景**：某中层管理者的职业发展规划\n\n**职业发展系统分析**：\n\n**影响职业发展的关键因素**：\n- **专业技能**：业务能力和专业知识\n- **管理能力**：团队领导和项目管理\n- **人际关系**：内外部网络和影响力\n- **学习能力**：持续学习和适应变化\n- **个人品牌**：行业声誉和知名度\n\n**现状评估**：\n- **专业技能**：8/10（优势）\n- **管理能力**：6/10（需要提升）\n- **人际关系**：5/10（明显短板）\n- **学习能力**：7/10（较好）\n- **个人品牌**：4/10（严重不足）\n\n**限制因素分析**：\n- **主要约束**：人际关系能力\n- **影响机制**：限制了晋升机会和资源获取\n- **连锁反应**：影响个人品牌建设和职业机会\n\n**杠杆点策略设计**：\n\n**核心杠杆点**：建设关键人际关系\n- **内部关系**：与上级、同级、下级建立良好关系\n- **外部关系**：与客户、合作伙伴、行业专家建立联系\n- **策略关系**：识别对职业发展最关键的人际关系\n\n**具体实施方案**：\n\n**第一阶段：内部关系建设（3个月）**\n- **向上管理**：主动与上级沟通，了解期望和需求\n- **横向协作**：与同级部门建立合作关系\n- **向下领导**：提升团队管理和激励能力\n\n**第二阶段：外部网络拓展（6个月）**\n- **行业活动**：积极参加行业会议和论坛\n- **专业社群**：加入相关的专业组织和社群\n- **导师关系**：寻找行业内的导师和顾问\n\n**第三阶段：影响力建设（12个月）**\n- **内容分享**：在专业平台分享见解和经验\n- **演讲机会**：争取在会议和活动中演讲\n- **媒体曝光**：接受行业媒体的采访和报道\n\n**杠杆效应**：\n- **职业机会**：获得更多的内部晋升和外部机会\n- **资源获取**：更容易获得项目资源和支持\n- **个人品牌**：行业影响力和知名度显著提升\n- **薪资增长**：职位和薪资水平大幅提升\n\n#### **案例4：个人财务管理的杠杆点**\n\n**场景**：某年轻职场人士的财务状况改善\n\n**财务系统分析**：\n\n**收支结构分析**：\n- **月收入**：15000元\n- **固定支出**：房租4000元，生活费3000元，保险500元\n- **可变支出**：娱乐2000元，购物2000元，其他1000元\n- **储蓄**：2500元（储蓄率16.7%）\n\n**财务目标**：\n- **短期目标**：建立应急基金（6个月支出）\n- **中期目标**：购房首付（100万元）\n- **长期目标**：财务自由（被动收入覆盖支出）\n\n**限制因素识别**：\n- **储蓄率偏低**：16.7%的储蓄率难以实现中长期目标\n- **投资知识缺乏**：资金主要放在银行，收益率低\n- **消费习惯**：可变支出占比过高，缺乏控制\n\n**杠杆点策略**：\n\n**核心杠杆点1：提升储蓄率**\n- **支出优化**：\n  - 娱乐支出从2000元减少到1200元\n  - 购物支出从2000元减少到1000元\n  - 其他支出从1000元减少到500元\n- **收入提升**：\n  - 发展副业，增加月收入2000元\n  - 提升主业技能，争取加薪\n\n**核心杠杆点2：投资理财能力**\n- **知识学习**：\n  - 系统学习投资理财知识\n  - 了解不同投资工具的特点\n  - 建立适合自己的投资策略\n- **实践应用**：\n  - 开始定投指数基金\n  - 逐步提高投资比例\n  - 建立多元化投资组合\n\n**实施效果**：\n- **储蓄率提升**：从16.7%提升到35%\n- **月储蓄金额**：从2500元提升到6000元\n- **投资收益率**：从2%提升到8%\n- **财务目标实现**：购房首付目标提前2年实现\n\n### 🌟 杠杆点思维的高级应用\n\n#### **1. 系统性杠杆点识别**\n- **多层次分析**：从个人、团队、组织、行业多个层次识别杠杆点\n- **时间维度考虑**：区分短期、中期、长期的不同杠杆点\n- **影响力评估**：评估不同杠杆点的影响范围和持续时间\n\n#### **2. 杠杆点的组合应用**\n- **协同效应**：多个杠杆点的组合使用\n- **时序安排**：合理安排杠杆点的实施顺序\n- **资源配置**：在不同杠杆点之间合理分配资源\n\n#### **3. 动态杠杆点管理**\n- **持续监控**：监控杠杆点的有效性变化\n- **适时调整**：根据环境变化调整杠杆点策略\n- **新杠杆点发现**：持续寻找新的杠杆点机会\n\n### 🌟 成年人的杠杆点智慧\n\n#### **在企业管理中**：\n- **约束理论应用**：识别和管理生产经营中的瓶颈\n- **组织变革**：找到推动组织变革的关键杠杆点\n- **战略执行**：识别战略实施的关键成功因素\n\n#### **在个人发展中**：\n- **能力建设**：识别最能提升个人价值的核心能力\n- **关系建设**：建设对职业发展最关键的人际关系\n- **时间管理**：找到最能提升效率的时间管理方法\n\n#### **在投资理财中**：\n- **资产配置**：找到最能影响投资回报的关键因素\n- **风险管理**：识别最需要防范的关键风险点\n- **财富增长**：找到最能加速财富积累的杠杆点\n\n记住，杠杆点思维的核心是用最小的努力产生最大的改变。掌握这种思维方式，你就能在复杂的世界中找到关键的突破点，实现高效的系统改进和个人发展。\n\n---",
      "subsections": [
        {
          "id": "-",
          "title": "🌍 企业管理中的约束理论应用",
          "type": "content",
          "content": ""
        },
        {
          "id": "-",
          "title": "🎭 个人发展中的杠杆点思维",
          "type": "content",
          "content": ""
        },
        {
          "id": "-",
          "title": "🌟 杠杆点思维的高级应用",
          "type": "content",
          "content": ""
        },
        {
          "id": "-",
          "title": "🌟 成年人的杠杆点智慧",
          "type": "content",
          "content": ""
        }
      ]
    },
    {
      "id": "-",
      "title": "🏠 生活应用提示",
      "type": "life-application",
      "content": "### 今天就可以尝试：\n1. **瓶颈观察**：找一个你经常参与的活动，观察其中的瓶颈环节\n2. **杠杆点思考**：想想在学习或生活中，哪些小改变可能带来大影响\n3. **优先级排序**：列出你想改进的几个方面，按照杠杆效应排序\n\n### 明天的小挑战：\n选择一个你想要改进的系统（如学习方法、时间管理等），用今天学到的方法找出其限制因素和杠杆点。\n\n---",
      "subsections": [
        {
          "id": "-",
          "title": "今天就可以尝试：",
          "type": "content",
          "content": ""
        },
        {
          "id": "-",
          "title": "明天的小挑战：",
          "type": "content",
          "content": ""
        }
      ]
    },
    {
      "id": "-",
      "title": "📚 课程小结",
      "type": "summary",
      "content": "**今天你学会了**：\n- ✅ 理解限制因素：系统中限制整体表现的关键瓶颈\n- ✅ 识别杠杆点：能够用小力量撬动大变化的关键点\n- ✅ 分析方法：流程分析、问题追踪、资源约束等分析方法\n- ✅ 应用策略：优先解决限制因素，善用杠杆点实现高效改进\n\n**重要收获**：\n高效改进的系统智慧。掌握限制因素和杠杆点的识别方法，你就能避免平均用力，找到关键突破点，用最小的努力实现最大的改变。\n\n**下节课预告**：\n下节课我们将学习\"系统的适应性与鲁棒性/脆弱性\"——探索系统应对变化和冲击的能力！",
      "subsections": []
    }
  ],
  "metadata": {
    "convertedAt": "2025-07-01T05:30:09.451Z",
    "originalFile": "第68课-系统的限制因素与杠杆点-系统思维基础.md"
  },
  "moduleDir": "03-基础模块",
  "moduleName": "基础模块"
}