{
  "id": 52,
  "filename": "第52课-批判性思维的综合应用-批判性思维基础.md",
  "title": "第52课：批判性思维的综合应用（理性思维的完整实践）",
  "module": "批判性思维基础",
  "grade": "4年级及以上（已完成入门阶段学习）",
  "duration": "",
  "objective": "",
  "sections": [
    {
      "id": "-",
      "title": "📚 课程信息",
      "type": "general",
      "content": "- **学习时长**：23分钟（技能掌握15分钟 + 深度拓展8分钟）\n- **核心技能**：学会综合运用批判性思维技能，解决复杂的现实问题\n\n---",
      "subsections": []
    },
    {
      "id": "-",
      "title": "🎯 学习目标",
      "type": "general",
      "content": "学完这节课，你将能够：\n- ✅ 整合运用所有批判性思维技能\n- ✅ 系统性地分析和解决复杂问题\n- ✅ 在现实情境中灵活应用理性思维\n- ✅ 建立持续的批判性思维习惯\n\n---",
      "subsections": []
    },
    {
      "id": "-3",
      "title": "📖 概念导入（3分钟）",
      "type": "introduction",
      "content": "### 🤔 思考一下\n\n经过前面的学习，你已经掌握了批判性思维的各种技能：\n- **论证分析**：能够分析论证的结构和强度\n- **谬误识别**：能够识别各种逻辑谬误\n- **信息评估**：能够深入评估信息的可信度\n- **多元思维**：能够从多个角度思考问题\n- **视角理解**：能够理解不同的观点和立场\n\n但是，在现实生活中，问题往往是复杂的，需要综合运用多种技能。比如：\n\n**复杂问题示例**：\n学校正在考虑是否实行\"无作业日\"政策，你需要：\n- 分析支持和反对的论证\n- 识别讨论中的逻辑谬误\n- 评估相关研究和数据的可信度\n- 考虑不同利益相关者的观点\n- 寻找创新的解决方案\n\n这就需要**综合应用**批判性思维技能。\n\n### 💡 核心概念\n\n**批判性思维的综合应用**：在面对复杂问题时，系统性地运用多种批判性思维技能，进行全面分析和理性决策的过程\n\n**综合应用的特点**：\n- **系统性**：运用完整的思维框架\n- **灵活性**：根据情况选择合适的技能\n- **整合性**：将不同技能有机结合\n- **实践性**：解决真实的复杂问题\n\n**综合应用的核心流程**：\n1. **问题识别**：准确识别和定义问题\n2. **信息收集**：系统收集相关信息\n3. **多角度分析**：从不同角度分析问题\n4. **论证评估**：评估各种观点和论证\n5. **方案生成**：创造性地提出解决方案\n6. **决策制定**：基于分析做出理性决策\n7. **反思改进**：反思过程并持续改进\n\n**批判性思维技能地图**：\n- **基础技能**：观察、分析、推理、评估\n- **进阶技能**：论证分析、谬误识别、信息评估\n- **高级技能**：多元思维、视角理解、元认知\n- **综合应用**：系统整合、创新解决、持续改进\n\n---",
      "subsections": [
        {
          "id": "-",
          "title": "🤔 思考一下",
          "type": "reflection",
          "content": ""
        },
        {
          "id": "-",
          "title": "💡 核心概念",
          "type": "content",
          "content": ""
        }
      ]
    },
    {
      "id": "-5",
      "title": "🎬 案例展示（5分钟）",
      "type": "case-study",
      "content": "### 📚 案例1：学校\"智能手机管理\"政策制定\n\n**背景**：学校需要制定关于学生使用智能手机的管理政策\n\n**第一步：问题识别与定义**\n- **核心问题**：如何平衡手机的教育价值和潜在干扰\n- **相关问题**：安全需求、学习效果、社会公平、管理可行性\n- **问题边界**：校园内的手机使用，不涉及校外使用\n\n**第二步：信息收集与评估**\n- **研究数据收集**：\n  - 查找关于手机对学习影响的研究\n  - 了解其他学校的管理经验\n  - 收集本校师生家长的意见\n- **信息可信度评估**：\n  - 研究来源：权威教育机构 vs 商业机构\n  - 样本大小：大规模研究 vs 小样本调查\n  - 研究设计：对照实验 vs 观察研究\n  - 利益冲突：是否有商业利益影响\n\n**第三步：多角度分析**\n- **学生视角**：\n  - 支持者：便于学习查询、紧急联系、跟上时代\n  - 反对者：担心分心、同伴压力、网络成瘾\n- **教师视角**：\n  - 支持者：可用于教学创新、培养数字素养\n  - 反对者：干扰课堂秩序、增加管理负担\n- **家长视角**：\n  - 支持者：安全联系、适应社会发展\n  - 反对者：影响学习专注、担心不良内容\n- **管理层视角**：\n  - 考虑因素：教育效果、管理成本、法律责任、社会期望\n\n**第四步：论证分析**\n- **支持完全禁止的论证**：\n  - 前提：手机会分散学习注意力\n  - 证据：某些研究显示手机影响学习成绩\n  - 逻辑分析：证据是否充分？是否考虑了其他因素？\n- **支持有限使用的论证**：\n  - 前提：合理使用手机有教育价值\n  - 证据：一些学校的成功管理经验\n  - 逻辑分析：成功经验是否具有普适性？\n\n**第五步：谬误识别**\n- **稻草人谬误**：\"支持手机使用就是支持学生玩游戏\"\n- **滑坡谬误**：\"允许手机就会导致学生完全沉迷\"\n- **错误归因**：\"成绩下降都是因为手机\"\n- **虚假两难**：\"要么完全禁止，要么完全放开\"\n\n**第六步：创新方案生成**\n基于分析，提出创新解决方案：\n1. **分时段管理**：上课时间统一保管，课间和午休可使用\n2. **分年级政策**：不同年级采用不同的管理策略\n3. **教育整合**：将手机使用纳入数字素养教育\n4. **家校合作**：建立家校协同的管理机制\n5. **技术辅助**：使用技术手段辅助管理\n\n**第七步：方案评估与决策**\n- **可行性评估**：技术条件、人力资源、成本预算\n- **效果预测**：对学习、安全、管理的预期影响\n- **风险分析**：可能的问题和应对措施\n- **试点实施**：小范围试点，收集反馈，调整完善\n\n### 🏃 案例2：个人学习方法选择的综合分析\n\n**背景**：面对即将到来的重要考试，需要选择最适合的学习方法\n\n**综合分析过程**：\n\n**问题分析**：\n- 时间限制：距离考试还有2个月\n- 学科特点：需要同时准备数学、语文、英语\n- 个人情况：数学较弱，语文中等，英语较强\n- 目标设定：希望总分提高50分\n\n**信息收集**：\n- **学习方法研究**：\n  - 间隔重复法的科学依据\n  - 主动回忆vs被动复习的效果对比\n  - 多感官学习的优势\n- **个人数据分析**：\n  - 过去的学习效果记录\n  - 注意力集中时间段\n  - 不同方法的尝试结果\n\n**多角度考虑**：\n- **时间角度**：短期冲刺vs长期积累\n- **学科角度**：不同学科的不同需求\n- **个人角度**：学习风格、兴趣偏好、能力特点\n- **环境角度**：家庭环境、学校资源、同伴影响\n\n**方法论证分析**：\n- **大量刷题法**：\n  - 论证：通过大量练习提高熟练度\n  - 评估：对数学可能有效，但可能忽略理解\n- **深度理解法**：\n  - 论证：深入理解原理，举一反三\n  - 评估：有助于长期掌握，但时间可能不够\n- **综合平衡法**：\n  - 论证：结合理解和练习，因材施教\n  - 评估：更全面但需要精心设计\n\n**个性化方案设计**：\n1. **数学**：重点突破+适量练习（弱项优先）\n2. **语文**：阅读理解+写作技巧（稳中求进）\n3. **英语**：保持优势+查漏补缺（优势保持）\n4. **时间分配**：数学40%，语文30%，英语30%\n5. **方法组合**：理解+练习+复习+测试\n\n### 🌱 案例3：社会热点问题的理性分析\n\n**背景**：网络上关于\"是否应该推迟上学时间\"的激烈讨论\n\n**批判性思维综合应用**：\n\n**信息筛选与评估**：\n- **科学研究**：查找关于青少年睡眠和学习效果的权威研究\n- **实践案例**：了解已实施推迟上学的地区的实际效果\n- **多方观点**：收集学生、家长、教师、专家的不同观点\n\n**论证质量分析**：\n- **支持方论证**：\n  - \"青少年生物钟决定了晚睡晚起的自然规律\"\n  - 评估：有科学依据，但是否适用于所有学生？\n- **反对方论证**：\n  - \"推迟上学会影响家长上班时间安排\"\n  - 评估：现实考虑合理，但是否可以找到解决方案？\n\n**谬误识别**：\n- **人身攻击**：\"支持推迟的都是懒学生\"\n- **虚假两难**：\"要么7点上学，要么10点上学\"\n- **滑坡谬误**：\"推迟上学最终会导致学生越来越懒\"\n\n**多视角整合**：\n- **学生健康**：充足睡眠对身心发展的重要性\n- **教育效果**：上学时间对学习效率的影响\n- **社会协调**：与家长工作时间、社会运行的协调\n- **实施可行性**：交通、安全、成本等实际问题\n\n**创新解决思路**：\n- **弹性时间**：提供多个上学时间选择\n- **分阶段实施**：从高年级开始试点\n- **配套措施**：调整课外活动时间、提供早餐服务\n- **家校协作**：建立家校合作的支持体系\n\n**🔍 思考**：通过这些案例，你发现批判性思维的综合应用有什么特点和价值？\n\n---",
      "subsections": [
        {
          "id": "-1",
          "title": "📚 案例1：学校\"智能手机管理\"政策制定",
          "type": "case",
          "content": ""
        },
        {
          "id": "-2",
          "title": "🏃 案例2：个人学习方法选择的综合分析",
          "type": "case",
          "content": ""
        },
        {
          "id": "-3",
          "title": "🌱 案例3：社会热点问题的理性分析",
          "type": "case",
          "content": ""
        }
      ]
    },
    {
      "id": "-5",
      "title": "🧠 核心内容（5分钟）",
      "type": "core-content",
      "content": "### 🎯 批判性思维综合应用框架\n\n#### **第一阶段：问题定义与分析**\n- **问题识别**：\n  - 准确识别核心问题\n  - 区分症状和根本问题\n  - 明确问题的边界和范围\n- **问题分解**：\n  - 将复杂问题分解为子问题\n  - 识别问题之间的关联\n  - 确定优先级和重要性\n- **背景分析**：\n  - 了解问题的历史背景\n  - 分析当前的环境条件\n  - 识别相关的利益相关者\n\n#### **第二阶段：信息收集与评估**\n- **信息搜集策略**：\n  - 确定需要什么类型的信息\n  - 选择可靠的信息来源\n  - 使用多种信息收集方法\n- **信息质量评估**：\n  - 应用信息可信度评估技能\n  - 识别信息中的偏见和局限\n  - 交叉验证重要信息\n- **信息整理分析**：\n  - 对信息进行分类和整理\n  - 识别信息之间的模式和关联\n  - 发现信息空白和不一致\n\n#### **第三阶段：多角度分析**\n- **利益相关者分析**：\n  - 识别所有相关的利益群体\n  - 理解不同群体的观点和需求\n  - 分析利益冲突和共同点\n- **多维度思考**：\n  - 从不同时间维度分析（短期vs长期）\n  - 从不同空间维度分析（个人vs集体）\n  - 从不同价值维度分析（效率vs公平）\n- **情境分析**：\n  - 考虑不同情境下的不同方案\n  - 分析环境变化的影响\n  - 评估方案的适应性\n\n#### **第四阶段：论证分析与评估**\n- **论证结构分析**：\n  - 识别各种观点的论证结构\n  - 评估前提的真实性和相关性\n  - 检查推理过程的逻辑性\n- **谬误识别**：\n  - 系统检查各种逻辑谬误\n  - 分析谬误对结论的影响\n  - 提醒自己避免犯同样错误\n- **证据评估**：\n  - 评估证据的质量和充分性\n  - 寻找缺失的关键证据\n  - 考虑反驳证据的影响\n\n#### **第五阶段：方案生成与评估**\n- **创新思维**：\n  - 突破传统思维框架\n  - 寻找创新的解决方案\n  - 结合不同方案的优点\n- **方案设计**：\n  - 设计具体可行的实施方案\n  - 考虑实施的步骤和时间安排\n  - 预设应急预案和调整机制\n- **方案评估**：\n  - 评估方案的可行性\n  - 分析方案的成本和收益\n  - 考虑方案的风险和副作用\n\n#### **第六阶段：决策与实施**\n- **决策制定**：\n  - 基于分析结果做出理性决策\n  - 考虑决策的时机和方式\n  - 准备决策的沟通和解释\n- **实施规划**：\n  - 制定详细的实施计划\n  - 分配资源和责任\n  - 建立监控和评估机制\n- **持续改进**：\n  - 收集实施过程中的反馈\n  - 根据实际情况调整方案\n  - 总结经验教训\n\n### 📊 技能整合地图\n\n#### **基础技能层**\n- **观察技能**：准确观察现象和细节\n- **分析技能**：分解复杂问题和信息\n- **推理技能**：进行逻辑推理和推断\n- **评估技能**：评判信息和论证的质量\n\n#### **进阶技能层**\n- **论证分析**：分析论证的结构和强度\n- **谬误识别**：识别各种逻辑谬误\n- **信息评估**：深入评估信息可信度\n- **因果分析**：正确分析因果关系\n\n#### **高级技能层**\n- **多元思维**：避免非黑即白的思维\n- **视角理解**：理解不同的观点和立场\n- **元认知**：反思自己的思维过程\n- **责任意识**：诚实面对问题和承担责任\n\n#### **综合应用层**\n- **系统思维**：整体性地思考复杂问题\n- **创新思维**：创造性地解决问题\n- **协调能力**：协调不同观点和利益\n- **实践能力**：将思维转化为行动\n\n### 🔍 常见应用场景\n\n#### **学习决策场景**\n- **选课决策**：综合考虑兴趣、能力、未来规划\n- **学习方法选择**：基于科学研究和个人特点\n- **时间管理**：平衡不同学科和活动的时间分配\n- **目标设定**：设定合理可达的学习目标\n\n#### **人际关系场景**\n- **冲突解决**：理解不同观点，寻找解决方案\n- **团队合作**：协调不同成员的意见和贡献\n- **友谊维护**：处理友谊中的分歧和问题\n- **家庭沟通**：改善与家长的沟通和理解\n\n#### **社会参与场景**\n- **社会议题分析**：理性分析社会热点问题\n- **公民参与**：参与学校和社区的决策过程\n- **媒体素养**：批判性地分析媒体信息\n- **价值观形成**：基于理性思考形成价值观\n\n### ⚠️ 综合应用的挑战\n\n#### **挑战1：复杂性管理**\n- **问题**：现实问题往往非常复杂，涉及多个因素\n- **应对**：学会分解问题，逐步分析，保持耐心\n\n#### **挑战2：时间压力**\n- **问题**：现实中往往需要在有限时间内做决策\n- **应对**：提高分析效率，抓住关键要素，必要时寻求帮助\n\n#### **挑战3：情绪干扰**\n- **问题**：强烈情绪会影响理性思考\n- **应对**：学会情绪管理，在冷静状态下进行分析\n\n#### **挑战4：信息过载**\n- **问题**：信息太多可能导致分析瘫痪\n- **应对**：学会筛选关键信息，避免完美主义\n\n### 🛠️ 实用工具：综合分析检查表\n\n```\n批判性思维综合应用检查表\n\n问题定义：\n□ 是否准确识别了核心问题？\n□ 是否明确了问题的边界和范围？\n□ 是否分解了复杂问题？\n\n信息收集：\n□ 是否收集了充分的相关信息？\n□ 是否评估了信息的可信度？\n□ 是否识别了信息的偏见和局限？\n\n多角度分析：\n□ 是否考虑了所有相关的利益相关者？\n□ 是否从多个维度分析了问题？\n□ 是否理解了不同的观点和立场？\n\n论证评估：\n□ 是否分析了各种观点的论证结构？\n□ 是否识别了逻辑谬误？\n□ 是否评估了证据的质量？\n\n方案生成：\n□ 是否考虑了多种可能的解决方案？\n□ 是否评估了方案的可行性？\n□ 是否考虑了方案的风险和副作用？\n\n决策制定：\n□ 是否基于分析结果做出了理性决策？\n□ 是否考虑了实施的具体步骤？\n□ 是否建立了监控和调整机制？\n\n反思改进：\n□ 是否反思了整个分析过程？\n□ 是否识别了自己的偏见和局限？\n□ 是否总结了经验教训？\n```\n\n---",
      "subsections": [
        {
          "id": "-",
          "title": "🎯 批判性思维综合应用框架",
          "type": "content",
          "content": ""
        },
        {
          "id": "-",
          "title": "📊 技能整合地图",
          "type": "content",
          "content": ""
        },
        {
          "id": "-",
          "title": "🔍 常见应用场景",
          "type": "case",
          "content": ""
        },
        {
          "id": "-",
          "title": "⚠️ 综合应用的挑战",
          "type": "content",
          "content": ""
        },
        {
          "id": "-",
          "title": "🛠️ 实用工具：综合分析检查表",
          "type": "content",
          "content": ""
        }
      ]
    },
    {
      "id": "-5",
      "title": "🎮 交互练习（5分钟）",
      "type": "interactive-exercise",
      "content": "### 🎯 练习1：综合分析实践\n选择一个你关心的学校问题，进行综合分析：\n\n**问题**：_______\n\n**应用综合框架**：\n1. **问题定义**：_______\n2. **信息收集**：_______\n3. **多角度分析**：_______\n4. **论证评估**：_______\n5. **方案生成**：_______\n6. **决策建议**：_______\n\n### 🎯 练习2：技能整合检查\n回顾你在分析过程中使用了哪些批判性思维技能：\n\n**使用的技能**：\n□ 论证分析 □ 谬误识别 □ 信息评估\n□ 多元思维 □ 视角理解 □ 元认知反思\n□ 因果分析 □ 责任承担 □ 其他：_______\n\n**技能运用效果**：\n- 最有效的技能：_______\n- 需要加强的技能：_______\n- 新的发现：_______\n\n### 🎯 练习3：持续改进计划\n制定你的批判性思维持续改进计划：\n\n**现状评估**：\n- 我的强项：_______\n- 我的弱项：_______\n- 我的目标：_______\n\n**改进计划**：\n- 每天练习：_______\n- 每周反思：_______\n- 每月评估：_______\n\n✍️ **动手记录**：用综合分析检查表分析一个真实问题。\n\n---",
      "subsections": [
        {
          "id": "-1",
          "title": "🎯 练习1：综合分析实践",
          "type": "exercise",
          "content": ""
        },
        {
          "id": "-2",
          "title": "🎯 练习2：技能整合检查",
          "type": "exercise",
          "content": ""
        },
        {
          "id": "-3",
          "title": "🎯 练习3：持续改进计划",
          "type": "exercise",
          "content": ""
        }
      ]
    },
    {
      "id": "-2",
      "title": "✅ 技能确认测试（2分钟）",
      "type": "skill-test",
      "content": "### 🧪 快速测试\n\n**情况**：你的班级正在讨论是否举办一次大型的班级活动。有同学提出：\"我们应该举办这个活动，因为其他班级都举办了，我们不能落后。而且活动肯定会很有趣，大家都会喜欢的。反对的人就是不合群，不为班级着想。\"\n\n**问题**：运用批判性思维技能，这个论证存在哪些问题？\n\nA. 只是表达方式不够礼貌，论证本身没问题\nB. 存在多种逻辑谬误，缺乏充分的论证支持\nC. 只是个人观点，不需要过度分析\nD. 论证很有说服力，应该支持这个建议\n\n**正确答案**：B\n**解释**：这个论证存在多种批判性思维问题：1）**从众谬误**：\"其他班级都举办了\"不是充分理由；2）**缺乏证据**：\"肯定会很有趣\"、\"大家都会喜欢\"没有证据支持；3）**人身攻击**：将反对者标签为\"不合群\"、\"不为班级着想\"；4）**虚假两难**：暗示只有支持和反对两种选择；5）**论证不充分**：没有分析活动的具体内容、成本、时间安排等关键因素。正确的分析应该考虑：活动的教育价值、可行性、成本效益、时间安排、风险评估等，并听取不同观点，寻找最适合班级的方案。\n\n### ✨ 技能确认\n\n如果你能综合运用各种批判性思维技能，系统分析复杂问题，并做出理性决策，恭喜你掌握了批判性思维的综合应用技能！\n\n---",
      "subsections": [
        {
          "id": "-",
          "title": "🧪 快速测试",
          "type": "exercise",
          "content": ""
        },
        {
          "id": "-",
          "title": "✨ 技能确认",
          "type": "content",
          "content": ""
        }
      ]
    },
    {
      "id": "-8",
      "title": "💡 深度拓展：成人世界的理性决策智慧（8分钟）",
      "type": "deep-extension",
      "content": "### 🌍 商业决策中的批判性思维\n\n在成人世界里，批判性思维的综合应用是成功决策的关键：\n\n#### **案例1：创业项目的全面评估**\n\n**场景**：一位年轻人考虑是否辞职创业\n\n**综合分析过程**：\n\n**第一步：问题定义**\n- **核心问题**：是否应该在当前时点辞职创业\n- **相关因素**：个人能力、市场机会、财务状况、家庭责任、风险承受能力\n- **时间框架**：需要在3个月内做出决定\n\n**第二步：信息收集与评估**\n- **市场研究**：\n  - 目标市场规模和增长趋势\n  - 竞争对手分析和差异化机会\n  - 客户需求验证和付费意愿\n- **个人评估**：\n  - 技能匹配度和学习能力\n  - 领导力和团队建设经验\n  - 抗压能力和适应能力\n- **财务分析**：\n  - 启动资金需求和来源\n  - 现金流预测和盈亏平衡点\n  - 个人财务缓冲和家庭支出\n\n**第三步：多角度分析**\n- **个人发展角度**：\n  - 职业成长机会 vs 创业学习经验\n  - 稳定收入 vs 潜在高回报\n  - 工作生活平衡 vs 创业压力\n- **家庭责任角度**：\n  - 家庭财务安全需求\n  - 配偶和家人的支持程度\n  - 子女教育和生活质量影响\n- **市场时机角度**：\n  - 当前市场环境的有利因素\n  - 技术发展趋势和政策支持\n  - 竞争格局和进入壁垒\n\n**第四步：风险评估与管理**\n- **失败风险**：\n  - 项目失败的概率和影响\n  - 个人职业发展的机会成本\n  - 财务损失和债务风险\n- **风险缓解策略**：\n  - 保留部分时间的兼职工作\n  - 寻找合伙人分担风险\n  - 分阶段投入，降低初期风险\n  - 建立退出机制和备选方案\n\n**第五步：决策框架应用**\n- **量化分析**：\n  - 预期收益的概率分布\n  - 风险调整后的净现值\n  - 敏感性分析和情景分析\n- **定性评估**：\n  - 个人价值观和人生目标匹配度\n  - 后悔最小化原则\n  - 可逆性和学习价值\n\n**决策结果**：基于综合分析，制定分阶段创业计划，先兼职验证商业模式，再考虑全职投入。\n\n#### **案例2：企业战略转型的系统分析**\n\n**场景**：传统制造企业面临数字化转型决策\n\n**批判性思维应用**：\n\n**问题复杂性分析**：\n- **外部环境**：数字化趋势、客户需求变化、竞争格局演变\n- **内部能力**：技术基础、人才储备、财务实力、组织文化\n- **转型选择**：渐进式改进 vs 颠覆式创新、自主开发 vs 合作收购\n\n**信息收集与验证**：\n- **行业研究**：数字化转型的成功案例和失败教训\n- **技术评估**：相关技术的成熟度和发展趋势\n- **财务分析**：转型投入、预期收益、现金流影响\n- **组织评估**：员工技能、文化适应性、变革管理能力\n\n**多维度分析**：\n- **时间维度**：短期冲击 vs 长期竞争力\n- **范围维度**：局部试点 vs 全面转型\n- **深度维度**：表面数字化 vs 深度重构\n- **风险维度**：转型风险 vs 不转型风险\n\n**利益相关者协调**：\n- **股东**：关注投资回报和风险控制\n- **员工**：关注工作安全和技能发展\n- **客户**：关注服务质量和价值提升\n- **合作伙伴**：关注合作模式和利益分配\n\n**方案设计与评估**：\n- **渐进式方案**：分步骤、分领域逐步推进\n- **跨越式方案**：大胆投入，快速转型\n- **混合式方案**：核心业务稳定，新业务创新\n- **合作式方案**：与科技公司战略合作\n\n### 🎭 公共政策中的理性分析\n\n#### **案例3：城市交通政策的综合评估**\n\n**场景**：市政府考虑实施拥堵收费政策\n\n**政策分析框架**：\n\n**问题诊断**：\n- **交通拥堵现状**：高峰时段拥堵程度、经济损失评估\n- **根本原因分析**：供需失衡、价格机制缺失、替代方案不足\n- **国际经验借鉴**：伦敦、新加坡等城市的实施效果\n\n**利益相关者分析**：\n- **私家车主**：出行成本增加，但通行效率提升\n- **公共交通用户**：可能受益于更好的公交服务\n- **商业区经营者**：担心客流减少，但也可能受益于物流效率\n- **低收入群体**：可能面临更大的经济压力\n- **环保人士**：支持减少汽车使用和排放\n\n**政策设计考虑**：\n- **收费标准**：基于拥堵程度的动态定价\n- **收费区域**：核心商业区 vs 全市范围\n- **收费时间**：高峰时段 vs 全天候\n- **收入使用**：改善公共交通 vs 一般财政收入\n- **豁免政策**：紧急车辆、残疾人、低收入家庭\n\n**效果预测与评估**：\n- **交通效果**：拥堵缓解程度、通行时间节省\n- **经济效果**：收入增加、经济活动影响、就业影响\n- **社会效果**：公平性、接受度、行为改变\n- **环境效果**：排放减少、空气质量改善\n\n**实施策略**：\n- **试点先行**：小范围试点，收集数据和反馈\n- **公众参与**：广泛征求意见，提高政策透明度\n- **配套措施**：改善公共交通，提供替代方案\n- **监测调整**：建立监测机制，及时调整政策\n\n### 💪 个人发展中的理性规划\n\n#### **案例4：职业发展的长期规划**\n\n**场景**：30岁职场人士的职业发展规划\n\n**综合分析方法**：\n\n**自我评估**：\n- **能力盘点**：专业技能、软技能、学习能力\n- **兴趣分析**：真正的兴趣 vs 社会期望\n- **价值观澄清**：工作生活平衡、成就感、社会贡献\n- **性格特质**：内向外向、风险偏好、领导风格\n\n**外部环境分析**：\n- **行业趋势**：技术发展、市场变化、政策影响\n- **职业前景**：不同职业路径的发展空间\n- **竞争格局**：同行竞争者的优势和劣势\n- **机会识别**：新兴领域、跨界机会、创业可能\n\n**多路径规划**：\n- **专业深化路径**：在当前领域深入发展\n- **管理转型路径**：向管理岗位发展\n- **跨界发展路径**：进入相关或新兴领域\n- **创业路径**：自主创业或内部创业\n\n**风险评估与管理**：\n- **职业风险**：行业衰退、技能过时、年龄歧视\n- **财务风险**：收入波动、投资损失、家庭支出\n- **健康风险**：工作压力、生活方式、职业病\n- **关系风险**：家庭关系、职场关系、社交网络\n\n**行动计划制定**：\n- **短期目标**（1-2年）：技能提升、项目经验、网络建设\n- **中期目标**（3-5年）：职位晋升、专业认可、财务积累\n- **长期目标**（5-10年）：行业地位、财务自由、人生价值\n- **应急预案**：市场变化、健康问题、家庭变故的应对\n\n### 🌟 批判性思维的终身价值\n\n#### **1. 适应变化的能力**\n- **环境变化**：在快速变化的世界中保持适应性\n- **技术发展**：理性评估新技术的影响和机会\n- **社会变迁**：在社会变迁中保持理性和平衡\n- **个人成长**：在人生不同阶段做出明智选择\n\n#### **2. 复杂问题解决**\n- **系统思维**：从系统角度理解和解决复杂问题\n- **创新能力**：通过批判性思维产生创新解决方案\n- **协调能力**：在多方利益中寻找平衡和共赢\n- **执行能力**：将理性分析转化为有效行动\n\n#### **3. 领导力发展**\n- **决策能力**：基于理性分析做出高质量决策\n- **沟通能力**：清晰表达思路，说服和影响他人\n- **团队建设**：理解和协调团队成员的不同观点\n- **变革管理**：引导组织和团队应对变化\n\n#### **4. 社会责任**\n- **公民素养**：理性参与公共事务和社会讨论\n- **道德判断**：在复杂情况下做出符合道德的选择\n- **社会贡献**：用理性思维为社会问题提供解决方案\n- **文化传承**：将理性思维传递给下一代\n\n记住，批判性思维不是一次性的学习，而是终身的修炼。在复杂多变的现代社会中，它是我们最重要的思维工具和人生指南。\n\n---",
      "subsections": [
        {
          "id": "-",
          "title": "🌍 商业决策中的批判性思维",
          "type": "content",
          "content": ""
        },
        {
          "id": "-",
          "title": "🎭 公共政策中的理性分析",
          "type": "content",
          "content": ""
        },
        {
          "id": "-",
          "title": "💪 个人发展中的理性规划",
          "type": "content",
          "content": ""
        },
        {
          "id": "-",
          "title": "🌟 批判性思维的终身价值",
          "type": "content",
          "content": ""
        }
      ]
    },
    {
      "id": "-",
      "title": "🏠 生活应用提示",
      "type": "life-application",
      "content": "### 今天就可以尝试：\n1. **综合分析**：选择一个你面临的决策，用完整的框架进行分析\n2. **技能整合**：在日常讨论中有意识地运用多种批判性思维技能\n3. **反思总结**：每天花5分钟反思自己的思维过程\n\n### 明天的小挑战：\n建立你的\"批判性思维日记\"，记录每天运用批判性思维的情况，包括使用的技能、遇到的挑战、获得的收获。\n\n---",
      "subsections": [
        {
          "id": "-",
          "title": "今天就可以尝试：",
          "type": "content",
          "content": ""
        },
        {
          "id": "-",
          "title": "明天的小挑战：",
          "type": "content",
          "content": ""
        }
      ]
    },
    {
      "id": "-",
      "title": "📚 课程小结",
      "type": "summary",
      "content": "**今天你学会了**：\n- ✅ 掌握批判性思维综合应用的六阶段框架：问题定义、信息收集、多角度分析、论证评估、方案生成、决策实施\n- ✅ 理解技能整合地图：从基础技能到综合应用的完整体系\n- ✅ 学会应对综合应用的挑战：复杂性管理、时间压力、情绪干扰、信息过载\n- ✅ 建立持续改进的习惯：反思、评估、调整、提升\n\n**重要收获**：\n理性思维的完整实践。通过综合运用所有批判性思维技能，你已经具备了在复杂世界中进行理性分析和明智决策的能力。这不仅是学习技能，更是人生智慧，将伴随你一生的成长和发展。\n\n**批判性思维基础模块完成**：\n恭喜你完成了批判性思维基础模块的全部学习！你已经从入门阶段的基础技能，发展到基础阶段的系统应用。接下来，你将进入更高阶段的学习，探索更深层的思维奥秘。\n\n**下一步学习建议**：\n继续保持批判性思维的练习和应用，在实践中不断完善和提升。记住，真正的智慧来自于将所学知识应用到现实生活中，为自己和社会创造价值。",
      "subsections": []
    }
  ],
  "metadata": {
    "convertedAt": "2025-07-01T05:30:09.438Z",
    "originalFile": "第52课-批判性思维的综合应用-批判性思维基础.md"
  },
  "moduleDir": "03-基础模块",
  "moduleName": "基础模块"
}