{
  "id": 32,
  "filename": "第32课-适应与进化-系统思维入门.md",
  "title": "第32课：适应与进化（在变化中成长和发展）",
  "module": "系统思维入门",
  "grade": "4年级及以上",
  "duration": "",
  "objective": "",
  "sections": [
    {
      "id": "-",
      "title": "📚 课程信息",
      "type": "general",
      "content": "- **学习时长**：23分钟（技能掌握15分钟 + 深度拓展8分钟）\n- **核心技能**：理解适应与进化机制，学会在变化中持续发展\n\n---",
      "subsections": []
    },
    {
      "id": "-",
      "title": "🎯 学习目标",
      "type": "general",
      "content": "学完这节课，你将能够：\n- ✅ 理解适应与进化的本质和重要意义\n- ✅ 识别和分析系统的适应能力和进化特征\n- ✅ 学会培养个人和团队的适应进化能力\n- ✅ 运用适应进化思维应对变化和挑战\n\n---",
      "subsections": []
    },
    {
      "id": "-3",
      "title": "📖 概念导入（3分钟）",
      "type": "introduction",
      "content": "### 🤔 思考一下\n\n想想这些有趣的现象：\n- 为什么有些同学能快速适应新的学习环境和方法？\n- 为什么有些物种能在环境变化中生存，有些却灭绝了？\n- 为什么有些公司能在市场变化中越来越强，有些却倒闭了？\n- 为什么有些人能在困难中成长，有些却被困难击倒？\n\n这些都体现了**适应与进化**的神奇力量！\n\n### 💡 核心概念\n\n**适应**：系统根据环境变化调整自身结构和行为，以维持生存和发展的能力\n**进化**：系统在适应过程中不断改进和升级，实现质的飞跃和发展\n\n**适应与进化的特点**：\n- **主动性**：主动感知和响应环境变化\n- **学习性**：从经验中学习和改进\n- **创新性**：在适应中产生新的能力和特征\n- **持续性**：是一个持续不断的过程\n\n**适应与进化的类型**：\n- **被动适应vs主动适应**：被迫调整vs主动变革\n- **渐进进化vs跃迁进化**：逐步改进vs突破性变化\n- **个体适应vs群体适应**：个人层面vs集体层面\n- **结构适应vs功能适应**：改变结构vs改变功能\n\n**适应与进化思维的核心**：在变化中寻找机会，在挑战中实现成长！\n\n---",
      "subsections": [
        {
          "id": "-",
          "title": "🤔 思考一下",
          "type": "reflection",
          "content": ""
        },
        {
          "id": "-",
          "title": "💡 核心概念",
          "type": "content",
          "content": ""
        }
      ]
    },
    {
      "id": "-5",
      "title": "🎬 案例展示（5分钟）",
      "type": "case-study",
      "content": "### 📚 场景1：小明的学习方法进化\n\n**变化挑战**：小明升入初中后，发现小学的学习方法不再有效\n\n**适应进化过程**：\n\n**第一阶段：被动适应**\n- **问题发现**：成绩下降，感到学习压力增大\n- **初步调整**：增加学习时间，但效果不明显\n- **困惑状态**：不知道问题出在哪里，有些焦虑\n\n**第二阶段：主动探索**\n- **问题分析**：意识到是学习方法的问题，不是努力程度\n- **方法尝试**：尝试不同的学习方法和策略\n- **经验积累**：记录哪些方法有效，哪些无效\n\n**第三阶段：系统优化**\n- **方法整合**：将有效的方法组合成个人学习系统\n- **持续改进**：根据不同科目和情况调整方法\n- **能力提升**：不仅成绩提高，学习能力也显著增强\n\n**第四阶段：创新突破**\n- **方法创新**：结合个人特点创造独特的学习方法\n- **帮助他人**：将经验分享给其他同学\n- **元认知发展**：学会了如何学习和如何适应\n\n**进化成果**：\n- 学习成绩稳步提升，排名进入前列\n- 学习效率大幅提高，有更多时间发展兴趣\n- 适应能力增强，面对新挑战更有信心\n- 帮助同学，成为学习方法的\"小专家\"\n\n### 🏃 场景2：班级文化的适应进化\n\n**环境变化**：班级换了新班主任，管理风格完全不同\n\n**集体适应进化**：\n\n**初期冲突阶段**：\n- **文化冲突**：新老师的要求与原有习惯不符\n- **抵触情绪**：部分同学不适应，产生抵触心理\n- **混乱状态**：班级秩序暂时混乱，效率下降\n\n**磨合适应阶段**：\n- **沟通增加**：师生之间增加沟通，相互了解\n- **规则调整**：在保持原则的基础上适当调整规则\n- **角色重新定位**：班干部和同学重新找到自己的位置\n\n**协同进化阶段**：\n- **优势结合**：结合新老师的优势和班级原有优点\n- **创新实践**：尝试新的班级管理和活动方式\n- **文化融合**：形成新的班级文化和行为规范\n\n**升级发展阶段**：\n- **能力提升**：班级整体能力和凝聚力显著提升\n- **特色形成**：形成独特的班级特色和竞争优势\n- **影响扩大**：成为学校的优秀班级典型\n\n**进化效果**：\n- 班级成绩整体提升，各项评比名列前茅\n- 同学关系更加和谐，团队协作能力增强\n- 创新活动频出，班级影响力扩大\n- 为未来面对变化积累了宝贵经验\n\n### 🌱 场景3：个人兴趣的适应发展\n\n**小华的音乐之路**：从被动学习到主动创新的进化历程\n\n**适应进化轨迹**：\n\n**被动学习期**：\n- **外部推动**：家长要求学习钢琴，被动接受\n- **基础训练**：按照传统方法练习基本功\n- **兴趣萌芽**：逐渐发现音乐的美妙，产生兴趣\n\n**主动探索期**：\n- **风格拓展**：不满足于古典音乐，开始接触流行音乐\n- **技能融合**：将古典技巧与流行风格结合\n- **创作尝试**：开始尝试改编和创作简单的曲子\n\n**创新突破期**：\n- **跨界融合**：将音乐与其他兴趣（如编程）结合\n- **技术应用**：学习音乐制作软件，创作电子音乐\n- **平台展示**：在网络平台分享作品，获得认可\n\n**影响扩展期**：\n- **社群建设**：组建音乐兴趣小组，影响更多同学\n- **技能输出**：教授其他同学音乐制作技巧\n- **未来规划**：将音乐作为未来发展的重要方向\n\n**进化特征**：\n- 从被动接受到主动探索的心态转变\n- 从单一技能到综合能力的发展\n- 从个人兴趣到社会影响的扩展\n- 从模仿学习到创新创造的突破\n\n**🔍 思考**：什么因素决定了系统的适应进化能力？\n\n---",
      "subsections": [
        {
          "id": "-1",
          "title": "📚 场景1：小明的学习方法进化",
          "type": "case",
          "content": ""
        },
        {
          "id": "-2",
          "title": "🏃 场景2：班级文化的适应进化",
          "type": "case",
          "content": ""
        },
        {
          "id": "-3",
          "title": "🌱 场景3：个人兴趣的适应发展",
          "type": "case",
          "content": ""
        }
      ]
    },
    {
      "id": "-5",
      "title": "🧠 核心内容（5分钟）",
      "type": "core-content",
      "content": "### 🎯 适应与进化的系统理解\n\n#### **第一步：环境感知与分析**\n- **变化识别**：敏锐感知环境中的变化信号\n- **趋势判断**：分析变化的方向和发展趋势\n- **影响评估**：评估变化对系统的影响程度\n- **机会威胁分析**：识别变化中的机会和威胁\n\n#### **第二步：适应能力评估**\n- **现状分析**：评估系统当前的适应能力\n- **资源盘点**：盘点可用于适应的各种资源\n- **能力差距**：识别适应所需能力与现有能力的差距\n- **适应潜力**：评估系统的适应潜力和发展空间\n\n#### **第三步：适应策略制定**\n- **适应目标**：明确适应要达到的目标和标准\n- **策略选择**：选择合适的适应策略和路径\n- **资源配置**：为适应过程配置必要的资源\n- **风险管理**：识别和管理适应过程中的风险\n\n#### **第四步：进化实施与优化**\n- **渐进改进**：通过持续的小步改进实现适应\n- **突破创新**：在关键时刻实现突破性创新\n- **学习积累**：从适应过程中学习和积累经验\n- **能力升级**：将适应经验转化为系统能力\n\n### 📊 适应进化的核心机制\n\n#### **机制1：变异与选择**\n- **变异产生**：\n  - 随机变异：在尝试中产生的意外发现\n  - 定向变异：基于目标的主动改进\n  - 组合变异：不同元素的重新组合\n  - 跨界变异：从其他领域引入新元素\n\n- **选择压力**：\n  - 环境选择：环境变化产生的选择压力\n  - 竞争选择：与其他系统竞争产生的压力\n  - 目标选择：自设目标产生的选择标准\n  - 价值选择：基于价值观的选择机制\n\n#### **机制2：学习与记忆**\n- **经验学习**：\n  - 成功经验的总结和保留\n  - 失败教训的分析和避免\n  - 他人经验的观察和模仿\n  - 理论知识的学习和应用\n\n- **记忆机制**：\n  - 个体记忆：个人经验和知识的积累\n  - 组织记忆：团队和组织的知识管理\n  - 文化记忆：价值观和行为模式的传承\n  - 制度记忆：规则和流程的固化\n\n#### **机制3：反馈与调节**\n- **反馈循环**：\n  - 正反馈：成功经验的强化和放大\n  - 负反馈：错误行为的纠正和抑制\n  - 延迟反馈：长期效果的评估和调整\n  - 多层反馈：不同层次的反馈信息\n\n- **自我调节**：\n  - 自我监控：对自身状态的持续监控\n  - 自我诊断：对问题和不足的自我识别\n  - 自我修复：对错误和缺陷的自我纠正\n  - 自我优化：对性能和效率的自我提升\n\n### 🔍 适应进化的影响因素\n\n#### **内在因素**\n1. **学习能力**：\n   - 信息处理能力：快速理解和处理新信息\n   - 知识整合能力：将新旧知识有效整合\n   - 技能迁移能力：将已有技能应用到新情境\n   - 创新思维能力：产生新想法和解决方案\n\n2. **心理素质**：\n   - 开放心态：对新事物的接受和尝试态度\n   - 抗压能力：面对压力和挫折的承受能力\n   - 自信心：对自己适应能力的信心\n   - 成长心态：相信能力可以通过努力提升\n\n3. **资源基础**：\n   - 知识储备：已有的知识和经验基础\n   - 技能水平：现有的技能和能力水平\n   - 社会网络：可以提供支持的人际关系\n   - 物质条件：支持适应过程的物质资源\n\n#### **外在因素**\n1. **环境特征**：\n   - 变化速度：环境变化的快慢程度\n   - 变化幅度：环境变化的剧烈程度\n   - 可预测性：环境变化的可预测程度\n   - 资源丰富度：环境提供的资源多少\n\n2. **支持系统**：\n   - 教育支持：获得学习和发展的机会\n   - 社会支持：来自家庭、朋友、社会的支持\n   - 制度支持：有利于适应的制度和政策\n   - 技术支持：可以利用的技术工具和平台\n\n### ⚠️ 适应进化的常见障碍\n\n#### **障碍1：固化思维**\n❌ **表现**：思维模式僵化，不愿意改变\n✅ **克服方法**：培养成长心态，主动学习新知识\n\n#### **障碍2：恐惧变化**\n❌ **表现**：害怕变化带来的不确定性和风险\n✅ **克服方法**：逐步适应，从小变化开始练习\n\n#### **障碍3：能力不足**\n❌ **表现**：缺乏适应所需的知识和技能\n✅ **克服方法**：持续学习，提升核心能力\n\n#### **障碍4：资源限制**\n❌ **表现**：缺乏支持适应的必要资源\n✅ **克服方法**：创造性利用资源，寻求外部支持\n\n### 🛠️ 实用工具：适应进化能力评估表\n\n```\n适应进化能力评估表\n\n环境分析：\n当前面临的主要变化：_______\n变化的影响程度：_______ (高/中/低)\n变化的紧迫性：_______ (高/中/低)\n变化中的机会：_______\n变化中的威胁：_______\n\n适应能力评估：\n学习能力：_______ (强/中/弱)\n心理素质：_______ (强/中/弱)\n资源基础：_______ (丰富/一般/缺乏)\n支持系统：_______ (完善/一般/不足)\n\n适应策略：\n短期适应目标：_______\n长期进化目标：_______\n主要适应策略：_______\n资源配置计划：_______\n\n行动计划：\n第一步行动：_______\n关键里程碑：_______\n成功标准：_______\n风险预案：_______\n\n进化跟踪：\n学习收获：_______\n能力提升：_______\n经验积累：_______\n下一步计划：_______\n```\n\n---",
      "subsections": [
        {
          "id": "-",
          "title": "🎯 适应与进化的系统理解",
          "type": "content",
          "content": ""
        },
        {
          "id": "-",
          "title": "📊 适应进化的核心机制",
          "type": "content",
          "content": ""
        },
        {
          "id": "-",
          "title": "🔍 适应进化的影响因素",
          "type": "content",
          "content": ""
        },
        {
          "id": "-",
          "title": "⚠️ 适应进化的常见障碍",
          "type": "content",
          "content": ""
        },
        {
          "id": "-",
          "title": "🛠️ 实用工具：适应进化能力评估表",
          "type": "content",
          "content": ""
        }
      ]
    },
    {
      "id": "-5",
      "title": "🎮 交互练习（5分钟）",
      "type": "interactive-exercise",
      "content": "### 🎯 练习1：适应能力诊断\n分析下面情况的适应挑战和机会：\n\n**情况**：学校引入了新的在线学习平台，要求所有学生必须掌握\n\n**适应分析**：\n- **主要挑战**：_______\n- **潜在机会**：_______\n- **需要的能力**：_______\n- **可用资源**：_______\n\n**适应策略**：\n1. _______\n2. _______\n3. _______\n\n### 🎯 练习2：进化路径设计\n为下面的发展目标设计进化路径：\n\n**目标**：成为班级里的\"学习达人\"\n\n**进化路径设计**：\n- **当前状态**：_______\n- **第一阶段目标**：_______\n- **第二阶段目标**：_______\n- **最终目标**：_______\n\n**关键能力发展**：\n- **核心能力1**：_______\n- **核心能力2**：_______\n- **核心能力3**：_______\n\n### 🎯 练习3：个人适应计划\n为你面临的一个实际变化制定适应计划：\n\n**面临的变化**：_______\n\n**适应计划**：\n- **适应目标**：_______\n- **主要策略**：_______\n- **行动步骤**：_______\n- **时间安排**：_______\n\n**能力发展计划**：\n- **需要学习的知识**：_______\n- **需要培养的技能**：_______\n- **需要改变的习惯**：_______\n\n**支持系统**：\n- **寻求帮助的人**：_______\n- **利用的资源**：_______\n- **创造的条件**：_______\n\n✍️ **动手记录**：请认真制定你的个人适应进化计划。\n\n---",
      "subsections": [
        {
          "id": "-1",
          "title": "🎯 练习1：适应能力诊断",
          "type": "exercise",
          "content": ""
        },
        {
          "id": "-2",
          "title": "🎯 练习2：进化路径设计",
          "type": "exercise",
          "content": ""
        },
        {
          "id": "-3",
          "title": "🎯 练习3：个人适应计划",
          "type": "exercise",
          "content": ""
        }
      ]
    },
    {
      "id": "-2",
      "title": "✅ 技能确认测试（2分钟）",
      "type": "skill-test",
      "content": "### 🧪 快速测试\n\n**情况**：小李一直是班级的学习委员，但新学期班级重新选举，他落选了。他感到很沮丧，不知道该怎么办。\n\n**问题**：从适应与进化的角度，小李应该如何应对这个变化？\n\nA. 接受现实，以后不再参与班级事务\nB. 努力找回原来的职位，恢复以前的状态\nC. 分析落选原因，提升能力，寻找新的发展机会\nD. 抱怨选举不公平，等待下次机会\n\n**正确答案**：C\n**解释**：适应与进化思维要求我们将变化看作成长的机会。小李应该分析落选的原因，从中学习和改进，同时寻找新的方式为班级服务和展现自己的能力。这样不仅能适应变化，还能在变化中实现个人的进化和发展。\n\n### ✨ 技能确认\n\n如果你能敏锐感知环境变化，主动制定适应策略，在变化中学习成长并实现能力升级，恭喜你掌握了适应与进化的思维技能！\n\n---",
      "subsections": [
        {
          "id": "-",
          "title": "🧪 快速测试",
          "type": "exercise",
          "content": ""
        },
        {
          "id": "-",
          "title": "✨ 技能确认",
          "type": "content",
          "content": ""
        }
      ]
    },
    {
      "id": "-8",
      "title": "💡 深度拓展：成人世界的适应进化智慧（8分钟）",
      "type": "deep-extension",
      "content": "### 🌍 企业组织的适应进化\n\n在成人世界里，适应与进化能力是企业和个人生存发展的核心竞争力：\n\n#### **案例1：Netflix的数字化转型进化**\n\n**场景**：Netflix如何从DVD租赁公司进化为全球流媒体巨头\n\n**进化历程分析**：\n1. **第一次进化：从实体到在线（1997-2007）**：\n   - **环境变化**：互联网普及，在线服务需求增长\n   - **适应策略**：推出在线DVD租赁服务，建立邮寄系统\n   - **核心创新**：订阅制模式，无限期租赁，无滞纳金\n   - **竞争优势**：便利性和成本优势击败传统租赁店\n\n2. **第二次进化：从邮寄到流媒体（2007-2012）**：\n   - **环境变化**：宽带普及，流媒体技术成熟\n   - **适应策略**：推出流媒体服务，逐步减少DVD业务\n   - **技术投入**：大量投资流媒体技术和内容分发网络\n   - **用户体验**：即时观看，个性化推荐\n\n3. **第三次进化：从平台到内容制作（2012-至今）**：\n   - **环境变化**：内容成本上升，版权竞争激烈\n   - **适应策略**：投资原创内容，成为内容制作商\n   - **战略转型**：从技术公司转向娱乐公司\n   - **全球扩张**：适应不同国家的文化和监管环境\n\n**进化成功要素**：\n- **前瞻性思维**：提前预见技术和市场趋势\n- **勇于自我颠覆**：主动放弃盈利的旧业务\n- **持续创新投入**：大量投资新技术和新模式\n- **数据驱动决策**：用数据指导产品和内容决策\n- **文化适应能力**：快速适应全球不同市场\n\n**进化成果**：\n- 从小型DVD租赁公司成长为全球娱乐巨头\n- 市值超过传统媒体公司，重新定义娱乐行业\n- 推动整个行业向流媒体转型\n- 建立了强大的技术和内容护城河\n\n#### **案例2：微软的云计算转型**\n\n**场景**：微软如何从软件公司转型为云服务领导者\n\n**转型挑战**：\n- **传统优势衰落**：PC时代的Windows和Office优势在移动时代减弱\n- **新兴竞争**：谷歌、苹果、亚马逊等公司在新领域领先\n- **商业模式变化**：从一次性软件销售转向订阅和云服务\n- **企业文化转型**：从封闭竞争转向开放合作\n\n**适应进化策略**：\n1. **战略重新定位**：\n   - 从\"无处不在的计算\"转向\"移动优先，云优先\"\n   - 重新定义微软的使命和价值主张\n   - 将云计算确定为核心战略方向\n\n2. **技术能力重构**：\n   - 大量投资Azure云平台建设\n   - 收购和整合云计算相关技术\n   - 开发云原生的产品和服务\n\n3. **商业模式创新**：\n   - Office 365订阅模式替代一次性购买\n   - 提供混合云解决方案满足企业需求\n   - 建立合作伙伴生态系统\n\n4. **企业文化变革**：\n   - 从\"知道一切\"转向\"学习一切\"的文化\n   - 鼓励实验和快速失败\n   - 提升员工的成长心态和协作精神\n\n**转型成果**：\n- Azure成为全球第二大云平台\n- 公司市值重回全球前列\n- 成功转型为云计算和AI领域的领导者\n- 建立了新的竞争优势和增长引擎\n\n### 🎭 个人职业的适应进化\n\n#### **案例3：传统媒体人的数字化转型**\n\n**场景**：一位传统报纸记者如何适应数字媒体时代\n\n**职业挑战**：\n- **行业衰落**：传统纸媒发行量下降，广告收入减少\n- **技能过时**：传统写作技能在数字时代不够用\n- **竞争加剧**：自媒体和新媒体从业者大量涌入\n- **收入下降**：传统媒体薪资水平下降\n\n**适应进化过程**：\n1. **技能升级阶段**：\n   - **数字技能学习**：学习视频制作、社交媒体运营\n   - **多媒体能力**：从纯文字转向图文视频并重\n   - **数据分析**：学习用数据分析内容效果\n   - **用户思维**：从编辑思维转向用户思维\n\n2. **平台拓展阶段**：\n   - **多平台发布**：在微信、微博、抖音等平台发布内容\n   - **个人品牌建设**：建立个人专业形象和影响力\n   - **粉丝运营**：学习社群运营和粉丝互动\n   - **商业化探索**：尝试知识付费、广告合作等模式\n\n3. **价值重新定义阶段**：\n   - **专业深化**：在特定领域建立专业权威\n   - **内容创新**：创造独特的内容形式和观点\n   - **跨界合作**：与其他行业专家合作创造价值\n   - **教育输出**：将经验转化为教育产品\n\n**进化成果**：\n- 成功转型为知名自媒体人\n- 收入超过传统媒体时期\n- 建立了个人品牌和影响力\n- 获得了更大的创作自由度\n\n#### **案例4：制造业工程师的智能化转型**\n\n**场景**：传统制造业工程师面对工业4.0的挑战\n\n**转型压力**：\n- **技术革新**：人工智能、物联网、大数据改变制造业\n- **自动化趋势**：机器人和自动化设备替代人工\n- **技能要求变化**：需要掌握数字化和智能化技术\n- **职业发展瓶颈**：传统技能的价值在下降\n\n**适应策略实施**：\n1. **知识结构升级**：\n   - **新技术学习**：学习AI、IoT、大数据等新技术\n   - **跨学科融合**：将传统工程与信息技术结合\n   - **在线教育**：利用在线平台持续学习新知识\n   - **认证获取**：获得相关的专业认证和资质\n\n2. **实践能力提升**：\n   - **项目参与**：主动参与数字化改造项目\n   - **工具掌握**：学习使用新的设计和分析工具\n   - **数据分析**：培养数据分析和决策能力\n   - **系统思维**：从局部优化转向系统优化\n\n3. **职业角色转换**：\n   - **从执行到设计**：从执行者转向系统设计者\n   - **从技术到管理**：结合技术和管理能力\n   - **从内部到外部**：为其他企业提供咨询服务\n   - **从员工到创业**：利用专业能力创业\n\n**转型收获**：\n- 成为企业数字化转型的核心人才\n- 薪资水平显著提升，职业发展空间扩大\n- 建立了复合型的专业能力\n- 为未来的技术变革做好了准备\n\n### 💪 高级适应进化策略\n\n#### **1. 预见性适应**\n- **趋势研究**：持续关注行业和技术发展趋势\n- **情景规划**：为不同的未来情景制定应对方案\n- **早期信号**：识别变化的早期信号和弱信号\n- **前瞻布局**：提前布局未来需要的能力和资源\n\n#### **2. 系统性进化**\n- **能力组合**：建立多元化的能力组合\n- **网络效应**：利用网络效应放大个人影响力\n- **平台思维**：建立个人或组织的平台能力\n- **生态构建**：构建有利于自身发展的生态系统\n\n#### **3. 反脆弱性建设**\n- **冗余设计**：在关键能力上建立冗余\n- **选择权保留**：保留多种发展选择的可能性\n- **压力测试**：定期测试适应能力的极限\n- **快速恢复**：建立快速从挫折中恢复的能力\n\n### 🌟 成年人的适应进化智慧\n\n#### **在职业发展中**：\n- **终身学习**：将学习作为职业发展的核心能力\n- **敏捷适应**：快速响应市场和技术变化\n- **价值创造**：在变化中寻找和创造新的价值\n\n#### **在组织管理中**：\n- **文化建设**：建立鼓励学习和创新的组织文化\n- **能力建设**：持续提升组织的适应和创新能力\n- **生态思维**：从生态系统角度思考组织发展\n\n记住，真正的适应进化高手不是被动地应对变化，而是主动地在变化中寻找机会，在挑战中实现成长。适应是生存的基础，进化是发展的动力，两者结合才能在变化的世界中持续繁荣。\n\n---",
      "subsections": [
        {
          "id": "-",
          "title": "🌍 企业组织的适应进化",
          "type": "content",
          "content": ""
        },
        {
          "id": "-",
          "title": "🎭 个人职业的适应进化",
          "type": "content",
          "content": ""
        },
        {
          "id": "-",
          "title": "💪 高级适应进化策略",
          "type": "content",
          "content": ""
        },
        {
          "id": "-",
          "title": "🌟 成年人的适应进化智慧",
          "type": "content",
          "content": ""
        }
      ]
    },
    {
      "id": "-",
      "title": "🏠 生活应用提示",
      "type": "life-application",
      "content": "### 今天就可以尝试：\n1. **变化识别**：观察你周围正在发生的变化，分析其中的机会和挑战\n2. **能力评估**：评估你当前的适应能力，找出需要提升的方面\n3. **学习计划**：制定一个小的学习计划，开始培养新的适应能力\n\n### 明天的小挑战：\n使用适应进化能力评估表分析你面临的一个具体变化，制定详细的适应计划并开始实施第一步行动。\n\n---",
      "subsections": [
        {
          "id": "-",
          "title": "今天就可以尝试：",
          "type": "content",
          "content": ""
        },
        {
          "id": "-",
          "title": "明天的小挑战：",
          "type": "content",
          "content": ""
        }
      ]
    },
    {
      "id": "-",
      "title": "📚 课程小结",
      "type": "summary",
      "content": "**今天你学会了**：\n- ✅ 理解适应与进化的本质和重要意义\n- ✅ 掌握变异选择、学习记忆、反馈调节等核心机制\n- ✅ 学会培养个人和团队的适应进化能力\n- ✅ 运用适应进化思维应对变化和挑战\n\n**重要收获**：\n在变化中成长和发展。掌握适应与进化思维，你就能在任何变化中找到机会，在任何挑战中实现成长。这是在快速变化的世界中生存和发展的核心智慧。\n\n**系统思维入门模块总结**：\n恭喜你完成了系统思维入门模块的全部10课学习！你已经掌握了：\n- 整体与部分、相互影响、变化与平衡\n- 循环与重复、层次与结构、目标与手段\n- 原因与结果、约束与可能、反馈与调节、适应与进化\n\n这些系统思维的核心要素将帮助你用系统的眼光理解世界，用系统的方法解决问题，在复杂的世界中保持清晰的思考！\n\n**下个模块预告**：\n接下来我们将进入更高阶的思维训练，继续探索思维的奥秘，提升你的思维能力！",
      "subsections": []
    }
  ],
  "metadata": {
    "convertedAt": "2025-07-01T05:30:09.422Z",
    "originalFile": "第32课-适应与进化-系统思维入门.md"
  },
  "moduleDir": "02-入门模块",
  "moduleName": "入门模块"
}